Workbook

Sheet Maestro de Insumos 
A1: Codigo | B1: Descripción | C1: Tipo | D1: U.M. | E1: Grupo | F1: Vr.Unitario | G1: % IVA | H1: Vr.Neto | I1: Estado | J1: Sub-Analisis | K1: Stock Minimo | L1: Stock Maximo | M1: Devolutivo | N1: Adjuntos | O1: Iva Descontable | P1: Excluye IVA | Q1: Usuario Creación | R1: Fecha Creación | S1: Usuario Modificación | T1: Fecha Modificación
A2: 1 | B2: DURANTA | C2: M - INVENTARIO | D2: UND - UNIDAD | E2: 034 - OTRAS COMPRAS CTA | F2: 2000 | G2: 19 | H2: 2380 | I2: Activo | J2: NO | K2: 0 | L2: 0 | M2: NO | N2: NO | O2: SI | P2: NO | Q2: Cesar Augusto Rolon Cañon | R2: 15/11/2023
A3: 2 | B3: PALMA COLA DE ZORRO | C3: M - INVENTARIO | D3: UND - UNIDAD | E3: 034 - OTRAS COMPRAS CTA | F3: 500000 | G3: 19 | H3: 595000 | I3: Activo | J3: NO | K3: 0 | L3: 0 | M3: NO | N3: NO | O3: SI | P3: NO | Q3: Cesar Augusto Rolon Cañon | R3: 15/11/2023
A4: 3 | B4: HELICONIAS | C4: M - INVENTARIO | D4: UND - UNIDAD | E4: 034 - OTRAS COMPRAS CTA | F4: 5500 | G4: 19 | H4: 6545 | I4: Activo | J4: NO | K4: 0 | L4: 0 | M4: NO | N4: NO | O4: SI | P4: NO | Q4: Cesar Augusto Rolon Cañon | R4: 15/11/2023
A5: 4 | B5: GRAMA | C5: M - INVENTARIO | D5: M2 - METRO CUADRADO | E5: 034 - OTRAS COMPRAS CTA | F5: 9000 | G5: 19 | H5: 10710 | I5: Activo | J5: NO | K5: 0 | L5: 0 | M5: NO | N5: NO | O5: SI | P5: NO | Q5: Cesar Augusto Rolon Cañon | R5: 15/11/2023
A6: 5 | B6: CINTA ITALIANA | C6: M - INVENTARIO | D6: UND - UNIDAD | E6: 034 - OTRAS COMPRAS CTA | F6: 3500 | G6: 19 | H6: 4165 | I6: Activo | J6: NO | K6: 0 | L6: 0 | M6: NO | N6: NO | O6: SI | P6: NO | Q6: Cesar Augusto Rolon Cañon | R6: 15/11/2023
A7: 6 | B7: DIANELAS 0CCO | C7: M - INVENTARIO | D7: UND - UNIDAD | E7: 034 - OTRAS COMPRAS CTA | F7: 4000 | G7: 19 | H7: 4760 | I7: Activo | J7: NO | K7: 0 | L7: 0 | M7: NO | N7: NO | O7: SI | P7: NO | Q7: Cesar Augusto Rolon Cañon | R7: 15/11/2023
A8: 7 | B8: MANO DE OBRA 0CCO | C8: S - SERVICIOS | D8: UND - UNIDAD | E8: 037 - OTROS SERVICIOS CTA | F8: 1000000 | G8: 19 | H8: 1190000 | I8: Activo | J8: NO | K8: 0 | L8: 0 | M8: NO | N8: NO | O8: SI | P8: NO | Q8: Cesar Augusto Rolon Cañon | R8: 15/11/2023
A9: 8 | B9: DESAGUE PUSH AUTOMATICO SIN DESBORDE EN BRONCE | C9: M - INVENTARIO | D9: UND - UNIDAD | E9: 034 - OTRAS COMPRAS CTA | F9: 67143 | G9: 19 | H9: 79900 | I9: Activo | J9: NO | K9: 0 | L9: 0 | M9: NO | N9: NO | O9: SI | P9: NO | Q9: Cesar Augusto Rolon Cañon | R9: 15/11/2023
A10: 9 | B10: ACOPLE METALICO PARA MESNOCONTROL 50CM 1/2" | C10: M - INVENTARIO | D10: UND - UNIDAD | E10: 034 - OTRAS COMPRAS CTA | F10: 18403 | G10: 19 | H10: 21900 | I10: Activo | J10: NO | K10: 0 | L10: 0 | M10: NO | N10: NO | O10: SI | P10: NO | Q10: Cesar Augusto Rolon Cañon | R10: 15/11/2023
A11: 10 | B11: TAPON ROSCADO DE 1/2" | C11: M - INVENTARIO | D11: UND - UNIDAD | E11: 034 - OTRAS COMPRAS CTA | F11: 336 | G11: 19 | H11: 400 | I11: Activo | J11: NO | K11: 0 | L11: 0 | M11: NO | N11: NO | O11: SI | P11: NO | Q11: Cesar Augusto Rolon Cañon | R11: 15/11/2023
A12: 11 | B12: TAPON LISO DE 1/2" | C12: M - INVENTARIO | D12: UND - UNIDAD | E12: 034 - OTRAS COMPRAS CTA | F12: 252 | G12: 19 | H12: 300 | I12: Activo | J12: NO | K12: 0 | L12: 0 | M12: NO | N12: NO | O12: SI | P12: NO | Q12: Cesar Augusto Rolon Cañon | R12: 15/11/2023
A13: 12 | B13: TAPON ROSCADO DE 3/4" | C13: M - INVENTARIO | D13: UND - UNIDAD | E13: 034 - OTRAS COMPRAS CTA | F13: 798 | G13: 19 | H13: 950 | I13: Activo | J13: NO | K13: 0 | L13: 0 | M13: NO | N13: NO | O13: SI | P13: NO | Q13: Cesar Augusto Rolon Cañon | R13: 15/11/2023
... A17: 16 | B17: TUBO PVC DE PRESION 1" X 6MTS | C17: M - INVENTARIO | D17: UND - UNIDAD | E17: 034 - OTRAS COMPRAS CTA | F17: 26807 | G17: 19 | H17: 31900 | I17: Activo | J17: NO | K17: 0 | L17: 0 | M17: NO | N17: NO | O17: SI | P17: NO | Q17: Cesar Augusto Rolon Cañon | R17: 15/11/2023
A18: 17 | B18: CINTA TEFLON 3/4" X 15MTS | C18: M - INVENTARIO | D18: UND - UNIDAD | E18: 034 - OTRAS COMPRAS CTA | F18: 2200 | G18: 19 | H18: 2618 | I18: Activo | J18: NO | K18: 0 | L18: 0 | M18: NO | N18: NO | O18: SI | P18: NO | Q18: Cesar Augusto Rolon Cañon | R18: 15/11/2023 | S18: Direccion Administrativa | T18: 10/01/2024
A19: 18 | B19: REMOVEDOR LIMPIADOR PVC X 1/4 DE GALON | C19: M - INVENTARIO | D19: UND - UNIDAD | E19: 034 - OTRAS COMPRAS CTA | F19: 41933 | G19: 19 | H19: 49900 | I19: Activo | J19: NO | K19: 0 | L19: 0 | M19: NO | N19: NO | O19: SI | P19: NO | Q19: Cesar Augusto Rolon Cañon | R19: 15/11/2023 | S19: Ruben Dario Villabona Sarmiento | T19: 26/01/2024
A20: 19 | B20: SOLDADURA LIQUIDA PVC X 1/4 DE GALON MARCA CELTA | C20: M - INVENTARIO | D20: UND - UNIDAD | E20: 034 - OTRAS COMPRAS CTA | F20: 89500 | G20: 19 | H20: 106505 | I20: Activo | J20: NO | K20: 0 | L20: 0 | M20: NO | N20: NO | O20: SI | P20: NO | Q20: Cesar Augusto Rolon Cañon | R20: 15/11/2023 | S20: Ruben Dario Villabona Sarmiento | T20: 04/03/2024
A21: 20 | B21: ORINAL ARRECIFE REF 06106A001 | C21: M - INVENTARIO | D21: UND - UNIDAD | E21: 034 - OTRAS COMPRAS CTA | F21: 428571 | G21: 19 | H21: 510000 | I21: Activo | J21: NO | K21: 0 | L21: 0 | M21: NO | N21: NO | O21: SI | P21: NO | Q21: Cesar Augusto Rolon Cañon | R21: 15/11/2023
A22: 21 | B22: SANITARIO SMART ALONGADO COLOR BLANCO REF, O39181001 | C22: M - INVENTARIO | D22: UND - UNIDAD | E22: 034 - OTRAS COMPRAS CTA | F22: 411681 | G22: 19 | H22: 489900 | I22: Activo | J22: NO | K22: 0 | L22: 0 | M22: NO | N22: NO | O22: SI | P22: NO | Q22: Cesar Augusto Rolon Cañon | R22: 15/11/2023
A23: 22 | B23: SANITARIO ADRIÁTICO REF, O13181001 | C23: M - INVENTARIO | D23: UND - UNIDAD | E23: 034 - OTRAS COMPRAS CTA | F23: 604958 | G23: 19 | H23: 719900 | I23: Activo | J23: NO | K23: 0 | L23: 0 | M23: NO | N23: NO | O23: SI | P23: NO | Q23: Cesar Augusto Rolon Cañon | R23: 15/11/2023
A24: 23 | B24: SANITARIO POWER ONE REF, 010141001 | C24: M - INVENTARIO | D24: UND - UNIDAD | E24: 034 - OTRAS COMPRAS CTA | F24: 552941 | G24: 19 | H24: 658000 | I24: Activo | J24: NO | K24: 0 | L24: 0 | M24: NO | N24: NO | O24: SI | P24: NO | Q24: Cesar Augusto Rolon Cañon | R24: 15/11/2023
A25: 24 | B25: LAVAMANOS MARCA SENCO REFERENCIA FORTUNDA TIPO VESSEL COLOR BLANCO | C25: M - INVENTARIO | D25: UND - UNIDAD | E25: 034 - OTRAS COMPRAS CTA | F25: 142773 | G25: 19 | H25: 169900 | I25: Activo | J25: NO | K25: 0 | L25: 0 | M25: NO | N25: NO | O25: SI | P25: NO | Q25: Cesar Augusto Rolon Cañon | R25: 15/11/2023
A26: 25 | B26: GRIFERÍA MESNOCONTROL FÉNIX ALTA MARCA DECORCERAMICA CÓDIGO DG25CR001 | C26: M - INVENTARIO | D26: UND - UNIDAD | E26: 034 - OTRAS COMPRAS CTA | F26: 226891 | G26: 19 | H26: 270000 | I26: Activo | J26: NO | K26: 0 | L26: 0 | M26: NO | N26: NO | O26: SI | P26: NO | Q26: Cesar Augusto Rolon Cañon | R26: 15/11/2023
A27: 26 | B27: PANEL LED SOBREPONER CIRCULAR 1350 LÚMENES 18W LUZ FRÍA | C27: M - INVENTARIO | D27: UND - UNIDAD | E27: 034 - OTRAS COMPRAS CTA | F27: 31008 | G27: 19 | H27: 36900 | I27: Activo | J27: NO | K27: 0 | L27: 0 | M27: NO | N27: NO | O27: SI | P27: NO | Q27: Cesar Augusto Rolon Cañon | R27: 15/11/2023
A28: 27 | B28: PANEL LED 60X60 | C28: M - INVENTARIO | D28: UND - UNIDAD | E28: 034 - OTRAS COMPRAS CTA | F28: 100756 | G28: 19 | H28: 119900 | I28: Activo | J28: NO | K28: 0 | L28: 0 | M28: NO | N28: NO | O28: SI | P28: NO | Q28: Cesar Augusto Rolon Cañon | R28: 15/11/2023
A29: 28 | B29: SENSOR DE MESVIMIENTO PARA TECHO 360° | C29: M - INVENTARIO | D29: UND - UNIDAD | E29: 034 - OTRAS COMPRAS CTA | F29: 55546 | G29: 19 | H29: 66100 | I29: Activo | J29: NO | K29: 0 | L29: 0 | M29: NO | N29: NO | O29: SI | P29: NO | Q29: Cesar Augusto Rolon Cañon | R29: 15/11/2023
A30: 29 | B30: TOMA WETGUARD SEGURO INDUSTRIAL 15A - 277V L7-15P 2P 3W AMARILLO IP67 LEVITON REF. 25W34 | C30: M - INVENTARIO | D30: UND - UNIDAD | E30: 034 - OTRAS COMPRAS CTA | F30: 92654.52 | G30: 19 | H30: 110258.88 | I30: Activo | J30: NO | K30: 0 | L30: 0 | M30: NO | N30: NO | O30: SI | P30: NO | Q30: Cesar Augusto Rolon Cañon | R30: 15/11/2023 | S30: Ruben Dario Villabona Sarmiento | T30: 19/06/2024
A31: 30 | B31: CLAVIJA WETGUARD SEGURO INDUSTRIAL 15A - 277V L7-15P 2P 3W AMARILLO IP67 LEVITON REF. 24W34 | C31: M - INVENTARIO | D31: UND - UNIDAD | E31: 034 - OTRAS COMPRAS CTA | F31: 72136.15 | G31: 19 | H31: 85842.019 | I31: Activo | J31: NO | K31: 0 | L31: 0 | M31: NO | N31: NO | O31: SI | P31: NO | Q31: Cesar Augusto Rolon Cañon | R31: 15/11/2023 | S31: Ruben Dario Villabona Sarmiento | T31: 19/06/2024
A32: 31 | B32: TOMA DOBLE BLANCA CFGI | C32: M - INVENTARIO | D32: UND - UNIDAD | E32: 034 - OTRAS COMPRAS CTA | F32: 45126 | G32: 19 | H32: 53700 | I32: Activo | J32: NO | K32: 0 | L32: 0 | M32: NO | N32: NO | O32: SI | P32: NO | Q32: Cesar Augusto Rolon Cañon | R32: 15/11/2023
A33: 32 | B33: ARREGLO ESCRITORIO EN L DE 1,500CC0 | C33: S - SERVICIOS | D33: UND - UNIDAD | E33: 037 - OTROS SERVICIOS CTA | F33: 180000 | G33: 19 | H33: 214200 | I33: Activo | J33: NO | K33: 0 | L33: 0 | M33: NO | N33: NO | O33: SI | P33: NO | Q33: Cesar Augusto Rolon Cañon | R33: 15/11/2023 | S33: Ruben Dario Villabona Sarmiento | T33: 19/06/2024
A34: 33 | B34: ARREGLO ESCRITORIO DE 1,200CC0 | C34: S - SERVICIOS | D34: UND - UNIDAD | E34: 037 - OTROS SERVICIOS CTA | F34: 150000 | G34: 19 | H34: 178500 | I34: Activo | J34: NO | K34: 0 | L34: 0 | M34: NO | N34: NO | O34: SI | P34: NO | Q34: Cesar Augusto Rolon Cañon | R34: 15/11/2023
A35: 34 | B35: ARREGLO DE SILLAS ERGONOMICA0CC0 | C35: S - SERVICIOS | D35: UND - UNIDAD | E35: 037 - OTROS SERVICIOS CTA | F35: 100000 | G35: 19 | H35: 119000 | I35: Activo | J35: NO | K35: 0 | L35: 0 | M35: NO | N35: NO | O35: SI | P35: NO | Q35: Cesar Augusto Rolon Cañon | R35: 15/11/2023
A36: 35 | B36: ARREGLO DE SILLAS ASISTENCIAL0CC0 | C36: S - SERVICIOS | D36: UND - UNIDAD | E36: 037 - OTROS SERVICIOS CTA | F36: 60000 | G36: 19 | H36: 71400 | I36: Activo | J36: NO | K36: 0 | L36: 0 | M36: NO | N36: NO | O36: SI | P36: NO | Q36: Cesar Augusto Rolon Cañon | R36: 15/11/2023 | S36: Ruben Dario Villabona Sarmiento | T36: 19/06/2024
A37: 36 | B37: ARREGLO DE BIBLIOTECA 0CC0 | C37: S - SERVICIOS | D37: UND - UNIDAD | E37: 037 - OTROS SERVICIOS CTA | F37: 100000 | G37: 19 | H37: 119000 | I37: Activo | J37: NO | K37: 0 | L37: 0 | M37: NO | N37: NO | O37: SI | P37: NO | Q37: Cesar Augusto Rolon Cañon | R37: 15/11/2023
A38: 37 | B38: CILINDRO AJUSTABLE PARA SILLA ERGONOMICA | C38: M - INVENTARIO | D38: UND - UNIDAD | E38: 034 - OTRAS COMPRAS CTA | F38: 60000 | G38: 19 | H38: 71400 | I38: Activo | J38: NO | K38: 0 | L38: 0 | M38: NO | N38: NO | O38: SI | P38: NO | Q38: Cesar Augusto Rolon Cañon | R38: 15/11/2023
A39: 38 | B39: BASE ARAÑA PARA SILLA ERGONOMICA | C39: M - INVENTARIO | D39: UND - UNIDAD | E39: 034 - OTRAS COMPRAS CTA | F39: 65000 | G39: 19 | H39: 77350 | I39: Activo | J39: NO | K39: 0 | L39: 0 | M39: NO | N39: NO | O39: SI | P39: NO | Q39: Cesar Augusto Rolon Cañon | R39: 15/11/2023
A40: 39 | B40: RUEDA PARA SILLA DE OFICINA | C40: M - INVENTARIO | D40: UND - UNIDAD | E40: 034 - OTRAS COMPRAS CTA | F40: 5800 | G40: 19 | H40: 6902 | I40: Activo | J40: NO | K40: 0 | L40: 0 | M40: NO | N40: NO | O40: SI | P40: NO | Q40: Cesar Augusto Rolon Cañon | R40: 15/11/2023
A41: 40 | B41: SOPORTE PICOLORO PARA VIDRIO | C41: M - INVENTARIO | D41: UND - UNIDAD | E41: 034 - OTRAS COMPRAS CTA | F41: 62000 | G41: 19 | H41: 73780 | I41: Activo | J41: NO | K41: 0 | L41: 0 | M41: NO | N41: NO | O41: SI | P41: NO | Q41: Cesar Augusto Rolon Cañon | R41: 15/11/2023
A42: 41 | B42: VIDRIO SEPARADOR DE PUESTOS DE TRABAJO | C42: M - INVENTARIO | D42: UND - UNIDAD | E42: 034 - OTRAS COMPRAS CTA | F42: 135000 | G42: 19 | H42: 160650 | I42: Activo | J42: NO | K42: 0 | L42: 0 | M42: NO | N42: NO | O42: SI | P42: NO | Q42: Cesar Augusto Rolon Cañon | R42: 15/11/2023
A43: 42 | B43: MANTENIMIENTO LOCATIVO CC0 | C43: S - SERVICIOS | D43: UND - UNIDAD | E43: 037 - OTROS SERVICIOS CTA | F43: 0 | G43: 19 | H43: 0 | I43: Activo | J43: NO | K43: 0 | L43: 0 | M43: NO | N43: NO | O43: SI | P43: NO | Q43: Cesar Augusto Rolon Cañon | R43: 15/11/2023
A44: 43 | B44: TOPELLANTAS | C44: M - INVENTARIO | D44: UND - UNIDAD | E44: 034 - OTRAS COMPRAS CTA | F44: 32000 | G44: 19 | H44: 38080 | I44: Activo | J44: NO | K44: 0 | L44: 0 | M44: NO | N44: NO | O44: SI | P44: NO | Q44: Cesar Augusto Rolon Cañon | R44: 15/11/2023
A45: 44 | B45: JUEGO DE TORNILERIA PARA INSTALACION | C45: M - INVENTARIO | D45: UND - UNIDAD | E45: 034 - OTRAS COMPRAS CTA | F45: 2500 | G45: 19 | H45: 2975 | I45: Activo | J45: NO | K45: 0 | L45: 0 | M45: NO | N45: NO | O45: SI | P45: NO | Q45: Cesar Augusto Rolon Cañon | R45: 15/11/2023
A46: 45 | B46: MANTENIMIENTO PTAR 0CC0 | C46: S - SERVICIOS | D46: UND - UNIDAD | E46: 037 - OTROS SERVICIOS CTA | F46: 0 | G46: 19 | H46: 0 | I46: Activo | J46: NO | K46: 0 | L46: 0 | M46: NO | N46: NO | O46: SI | P46: NO | Q46: Cesar Augusto Rolon Cañon | R46: 15/11/2023
A47: 46 | B47: MANTENIMIENTO BOMBAS DE SUMINISTRO0CC0 | C47: S - SERVICIOS | D47: UND - UNIDAD | E47: 037 - OTROS SERVICIOS CTA | F47: 350000 | G47: 19 | H47: 416500 | I47: Activo | J47: NO | K47: 0 | L47: 0 | M47: NO | N47: NO | O47: SI | P47: NO | Q47: Cesar Augusto Rolon Cañon | R47: 15/11/2023
A48: 47 | B48: LAVADO DE TANQUE DE SUMINISTRO0CC0 | C48: S - SERVICIOS | D48: UND - UNIDAD | E48: 037 - OTROS SERVICIOS CTA | F48: 1100000 | G48: 19 | H48: 1309000 | I48: Activo | J48: NO | K48: 0 | L48: 0 | M48: NO | N48: NO | O48: SI | P48: NO | Q48: Cesar Augusto Rolon Cañon | R48: 15/11/2023
... A52: 51 | B52: TIJERAS PARA JARDINERIA | C52: M - INVENTARIO | D52: UND - UNIDAD | E52: 034 - OTRAS COMPRAS CTA | F52: 40252 | G52: 19 | H52: 47900 | I52: Activo | J52: NO | K52: 0 | L52: 0 | M52: NO | N52: NO | O52: SI | P52: NO | Q52: Cesar Augusto Rolon Cañon | R52: 15/11/2023
A53: 52 | B53: RASTRILLO METALICO 14 DIENTES CON CABO MADERA | C53: M - INVENTARIO | D53: UND - UNIDAD | E53: 034 - OTRAS COMPRAS CTA | F53: 26500 | G53: 19 | H53: 31535 | I53: Activo | J53: NO | K53: 0 | L53: 0 | M53: NO | N53: NO | O53: SI | P53: NO | Q53: Cesar Augusto Rolon Cañon | R53: 15/11/2023 | S53: Ruben Dario Villabona Sarmiento | T53: 04/03/2024
A54: 53 | B54: PALA PEQUEÑA | C54: M - INVENTARIO | D54: UND - UNIDAD | E54: 034 - OTRAS COMPRAS CTA | F54: 15042 | G54: 19 | H54: 17900 | I54: Activo | J54: NO | K54: 0 | L54: 0 | M54: NO | N54: NO | O54: SI | P54: NO | Q54: Cesar Augusto Rolon Cañon | R54: 15/11/2023
A55: 54 | B55: PALA REDONDA CON CABO | C55: M - INVENTARIO | D55: UND - UNIDAD | E55: 034 - OTRAS COMPRAS CTA | F55: 21250 | G55: 19 | H55: 25287.5 | I55: Activo | J55: NO | K55: 0 | L55: 0 | M55: NO | N55: NO | O55: SI | P55: NO | Q55: Cesar Augusto Rolon Cañon | R55: 15/11/2023 | S55: Ruben Dario Villabona Sarmiento | T55: 16/01/2024
A56: 55 | B56: ABONO ORGANICO | C56: M - INVENTARIO | D56: UND - UNIDAD | E56: 034 - OTRAS COMPRAS CTA | F56: 35294 | G56: 19 | H56: 42000 | I56: Activo | J56: NO | K56: 0 | L56: 0 | M56: NO | N56: NO | O56: SI | P56: NO | Q56: Cesar Augusto Rolon Cañon | R56: 15/11/2023
A57: 56 | B57: FUNDGICIDA | C57: M - INVENTARIO | D57: UND - UNIDAD | E57: 034 - OTRAS COMPRAS CTA | F57: 94874 | G57: 19 | H57: 112900 | I57: Activo | J57: NO | K57: 0 | L57: 0 | M57: NO | N57: NO | O57: SI | P57: NO | Q57: Cesar Augusto Rolon Cañon | R57: 15/11/2023
A58: 57 | B58: HERBICIDA | C58: M - INVENTARIO | D58: UND - UNIDAD | E58: 034 - OTRAS COMPRAS CTA | F58: 27647 | G58: 19 | H58: 32900 | I58: Activo | J58: NO | K58: 0 | L58: 0 | M58: NO | N58: NO | O58: SI | P58: NO | Q58: Cesar Augusto Rolon Cañon | R58: 15/11/2023
A59: 58 | B59: FERTILIZANTE X 25K | C59: M - INVENTARIO | D59: UND - UNIDAD | E59: 034 - OTRAS COMPRAS CTA | F59: 144958 | G59: 19 | H59: 172500 | I59: Activo | J59: NO | K59: 0 | L59: 0 | M59: NO | N59: NO | O59: SI | P59: NO | Q59: Cesar Augusto Rolon Cañon | R59: 15/11/2023
A60: 59 | B60: MANGUERA DE RIEGO PLASTICA X 100M | C60: M - INVENTARIO | D60: UND - UNIDAD | E60: 034 - OTRAS COMPRAS CTA | F60: 101597 | G60: 19 | H60: 120900 | I60: Activo | J60: NO | K60: 0 | L60: 0 | M60: NO | N60: NO | O60: SI | P60: NO | Q60: Cesar Augusto Rolon Cañon | R60: 15/11/2023
A61: 60 | B61: MANGUERA FLREFORZADA USO DURO 4 CAPAS X 100M | C61: M - INVENTARIO | D61: UND - UNIDAD | E61: 034 - OTRAS COMPRAS CTA | F61: 241933 | G61: 19 | H61: 287900 | I61: Activo | J61: NO | K61: 0 | L61: 0 | M61: NO | N61: NO | O61: SI | P61: NO | Q61: Cesar Augusto Rolon Cañon | R61: 15/11/2023
A62: 61 | B62: ASPERSORES DE RIEGO | C62: M - INVENTARIO | D62: UND - UNIDAD | E62: 034 - OTRAS COMPRAS CTA | F62: 9000 | G62: 19 | H62: 10710 | I62: Activo | J62: NO | K62: 0 | L62: 0 | M62: NO | N62: NO | O62: SI | P62: NO | Q62: Cesar Augusto Rolon Cañon | R62: 15/11/2023
A63: 62 | B63: REGISTRO DE BOLA PVC 1/2" | C63: M - INVENTARIO | D63: UND - UNIDAD | E63: 034 - OTRAS COMPRAS CTA | F63: 10000 | G63: 19 | H63: 11900 | I63: Activo | J63: NO | K63: 0 | L63: 0 | M63: NO | N63: NO | O63: SI | P63: NO | Q63: Cesar Augusto Rolon Cañon | R63: 15/11/2023 | S63: Ruben Dario Villabona Sarmiento | T63: 26/01/2024
A64: 63 | B64: ABRAZADERA METALICA | C64: M - INVENTARIO | D64: UND - UNIDAD | E64: 034 - OTRAS COMPRAS CTA | F64: 3361 | G64: 19 | H64: 4000 | I64: Activo | J64: NO | K64: 0 | L64: 0 | M64: NO | N64: NO | O64: SI | P64: NO | Q64: Cesar Augusto Rolon Cañon | R64: 15/11/2023
A65: 64 | B65: AMBIENTADOR BONAIRE AEROSOL 400 ML | C65: N - OTRAS COMPRAS | D65: UND - UNIDAD | E65: 016 - ELEMENTOS DE CAFETERIA CTA | F65: 8876 | G65: 19 | H65: 10562 | I65: Activo | J65: NO | K65: 0 | L65: 0 | M65: NO | N65: NO | O65: SI | P65: NO | Q65: Cesar Augusto Rolon Cañon | R65: 15/11/2023
A66: 65 | B66: AMBIENTADOR BONAIRE VARITAS DIFUSORAS VAINILLA 80 ML | C66: N - OTRAS COMPRAS | D66: UND - UNIDAD | E66: 016 - ELEMENTOS DE CAFETERIA CTA | F66: 13499 | G66: 19 | H66: 16064 | I66: Activo | J66: NO | K66: 0 | L66: 0 | M66: NO | N66: NO | O66: SI | P66: NO | Q66: Cesar Augusto Rolon Cañon | R66: 15/11/2023
A67: 66 | B67: AXION LIQUIDO LIMESN 750 ML | C67: N - OTRAS COMPRAS | D67: UND - UNIDAD | E67: 016 - ELEMENTOS DE CAFETERIA CTA | F67: 15345 | G67: 19 | H67: 18261 | I67: Activo | J67: NO | K67: 0 | L67: 0 | M67: NO | N67: NO | O67: SI | P67: NO | Q67: Cesar Augusto Rolon Cañon | R67: 15/11/2023
A68: 67 | B68: AZUCAR MANUELITA BLANCA ALTA PUREZA 1 KG (=) | C68: N - OTRAS COMPRAS | D68: UND - UNIDAD | E68: 016 - ELEMENTOS DE CAFETERIA CTA | F68: 6581 | G68: 19 | H68: 7831 | I68: Activo | J68: NO | K68: 0 | L68: 0 | M68: NO | N68: NO | O68: SI | P68: NO | Q68: Cesar Augusto Rolon Cañon | R68: 15/11/2023
A69: 68 | B69: BALDE PLASTICO 10 LT | C69: N - OTRAS COMPRAS | D69: UND - UNIDAD | E69: 016 - ELEMENTOS DE CAFETERIA CTA | F69: 8719 | G69: 19 | H69: 10376 | I69: Activo | J69: NO | K69: 0 | L69: 0 | M69: NO | N69: NO | O69: SI | P69: NO | Q69: Cesar Augusto Rolon Cañon | R69: 15/11/2023
A70: 69 | B70: BLANQUEADOR HIPOCLORITO SIN AROMA X 3,800 EKKOLOGICO | C70: N - OTRAS COMPRAS | D70: UND - UNIDAD | E70: 016 - ELEMENTOS DE CAFETERIA CTA | F70: 12566 | G70: 19 | H70: 14954 | I70: Activo | J70: NO | K70: 0 | L70: 0 | M70: NO | N70: NO | O70: SI | P70: NO | Q70: Cesar Augusto Rolon Cañon | R70: 15/11/2023
A71: 70 | B71: BOLSA BASURA 100 X 120 CALIBRE 2,3 BLANCA PAQ, X 6 | C71: N - OTRAS COMPRAS | D71: UND - UNIDAD | E71: 016 - ELEMENTOS DE CAFETERIA CTA | F71: 7361 | G71: 19 | H71: 8760 | I71: Activo | J71: NO | K71: 0 | L71: 0 | M71: NO | N71: NO | O71: SI | P71: NO | Q71: Cesar Augusto Rolon Cañon | R71: 15/11/2023
A72: 71 | B72: BOLSA BASURA 100 X 120 CALIBRE 2,3 NEGRA PAQ, X 6 | C72: N - OTRAS COMPRAS | D72: UND - UNIDAD | E72: 016 - ELEMENTOS DE CAFETERIA CTA | F72: 5410 | G72: 19 | H72: 6438 | I72: Activo | J72: NO | K72: 0 | L72: 0 | M72: NO | N72: NO | O72: SI | P72: NO | Q72: Cesar Augusto Rolon Cañon | R72: 15/11/2023
A73: 72 | B73: BOLSA BASURA 100 X 120 CALIBRE 2,3 ROJA PAQ, X 6 | C73: N - OTRAS COMPRAS | D73: UND - UNIDAD | E73: 016 - ELEMENTOS DE CAFETERIA CTA | F73: 7361 | G73: 19 | H73: 8760 | I73: Activo | J73: NO | K73: 0 | L73: 0 | M73: NO | N73: NO | O73: SI | P73: NO | Q73: Cesar Augusto Rolon Cañon | R73: 15/11/2023
A74: 73 | B74: BOLSA BASURA 100 X 120 CALIBRE 2,3 VERDE PAQ, X 6 | C74: N - OTRAS COMPRAS | D74: UND - UNIDAD | E74: 016 - ELEMENTOS DE CAFETERIA CTA | F74: 7361 | G74: 19 | H74: 8760 | I74: Activo | J74: NO | K74: 0 | L74: 0 | M74: NO | N74: NO | O74: SI | P74: NO | Q74: Cesar Augusto Rolon Cañon | R74: 15/11/2023
A75: 74 | B75: BOLSA BASURA 40 X 60 PARA PAPELERA VERDE CAL, 2,3 PAQ,X 6U, | C75: N - OTRAS COMPRAS | D75: UND - UNIDAD | E75: 016 - ELEMENTOS DE CAFETERIA CTA | F75: 1147 | G75: 19 | H75: 1365 | I75: Activo | J75: NO | K75: 0 | L75: 0 | M75: NO | N75: NO | O75: SI | P75: NO | Q75: Cesar Augusto Rolon Cañon | R75: 15/11/2023
... A184: 183 | B184: REFRIGERIOS | C184: N - OTRAS COMPRAS | D184: UND - UNIDAD | E184: 034 - OTRAS COMPRAS CTA | F184: 0 | G184: 19 | H184: 0 | I184: Activo | J184: NO | K184: 0 | L184: 0 | M184: NO | N184: NO | O184: SI | P184: NO | Q184: Cesar Augusto Rolon Cañon | R184: 15/11/2023
A185: 184 | B185: DOMINIO PAGINA WEB | C185: B - SOFTWARE | D185: AÑO - AÑO | E185: 031 - LICENCIAS | F185: 65000 | G185: 19 | H185: 77350 | I185: Activo | J185: NO | K185: 0 | L185: 0 | M185: NO | N185: NO | O185: SI | P185: NO | Q185: Cesar Augusto Rolon Cañon | R185: 15/11/2023 | S185: Andrea Nuñez | T185: 15/01/2025
A186: 185 | B186: HOSTING | C186: B - SOFTWARE | D186: AÑO - AÑO | E186: 031 - LICENCIAS | F186: 950000 | G186: 19 | H186: 1130500 | I186: Activo | J186: NO | K186: 0 | L186: 0 | M186: NO | N186: NO | O186: SI | P186: NO | Q186: Cesar Augusto Rolon Cañon | R186: 15/11/2023
A187: 186 | B187: 031 OFFICE 365 | C187: B - SOFTWARE | D187: MES - MES | E187: 031 - LICENCIAS | F187: 5900000 | G187: 19 | H187: 7021000 | I187: Activo | J187: NO | K187: 0 | L187: 0 | M187: NO | N187: NO | O187: SI | P187: NO | Q187: Cesar Augusto Rolon Cañon | R187: 15/11/2023
A188: 187 | B188: HOSTING SINCOSOFT | C188: B - SOFTWARE | D188: MES - MES | E188: 031 - LICENCIAS | F188: 5500000 | G188: 19 | H188: 6545000 | I188: Activo | J188: NO | K188: 0 | L188: 0 | M188: NO | N188: NO | O188: SI | P188: NO | Q188: Cesar Augusto Rolon Cañon | R188: 15/11/2023
A189: 188 | B189: PMA SINCO 0SERVICIO | C189: B - SOFTWARE | D189: AÑO - AÑO | E189: 031 - LICENCIAS | F189: 42000000 | G189: 19 | H189: 49980000 | I189: Activo | J189: NO | K189: 0 | L189: 0 | M189: NO | N189: NO | O189: SI | P189: NO | Q189: Cesar Augusto Rolon Cañon | R189: 15/11/2023
A190: 189 | B190: LICENCIA ADOBE CREATIVE CLOUD | C190: B - SOFTWARE | D190: MES - MES | E190: 031 - LICENCIAS | F190: 6000000 | G190: 19 | H190: 7140000 | I190: Activo | J190: NO | K190: 0 | L190: 0 | M190: NO | N190: NO | O190: SI | P190: NO | Q190: Cesar Augusto Rolon Cañon | R190: 15/11/2023 | S190: Sayde Hernandez Guerrero | T190: 01/12/2023
A191: 190 | B191: CIVIL 3D | C191: B - SOFTWARE | D191: AÑO - AÑO | E191: 031 - LICENCIAS | F191: 0 | G191: 19 | H191: 0 | I191: Activo | J191: NO | K191: 0 | L191: 0 | M191: NO | N191: NO | O191: SI | P191: NO | Q191: Cesar Augusto Rolon Cañon | R191: 15/11/2023
A192: 191 | B192: AUTOCAD LT | C192: B - SOFTWARE | D192: AÑO - AÑO | E192: 031 - LICENCIAS | F192: 0 | G192: 19 | H192: 0 | I192: Activo | J192: NO | K192: 0 | L192: 0 | M192: NO | N192: NO | O192: SI | P192: NO | Q192: Cesar Augusto Rolon Cañon | R192: 15/11/2023
A193: 192 | B193: LICENCIA KASPERSKY | C193: B - SOFTWARE | D193: AÑO - AÑO | E193: 031 - LICENCIAS | F193: 0 | G193: 19 | H193: 0 | I193: Activo | J193: NO | K193: 0 | L193: 0 | M193: NO | N193: NO | O193: SI | P193: NO | Q193: Cesar Augusto Rolon Cañon | R193: 15/11/2023
A194: 193 | B194: MANTENIMIENTO IMPRESORA | C194: B - SOFTWARE | D194: MES - MES | E194: 032 - MANTENIMIENTO DE EQUIPOS CTA | F194: 0 | G194: 19 | H194: 0 | I194: Activo | J194: NO | K194: 0 | L194: 0 | M194: NO | N194: NO | O194: SI | P194: NO | Q194: Cesar Augusto Rolon Cañon | R194: 15/11/2023
A195: 194 | B195: SERVICIO MANTENIMIENTO EQUIPOS TEC | C195: B - SOFTWARE | D195: UND - UNIDAD | E195: 032 - MANTENIMIENTO DE EQUIPOS CTA | F195: 0 | G195: 19 | H195: 0 | I195: Activo | J195: NO | K195: 0 | L195: 0 | M195: NO | N195: NO | O195: SI | P195: NO | Q195: Cesar Augusto Rolon Cañon | R195: 15/11/2023
A196: 195 | B196: COMPUTADOR PORTATIL | C196: E - ACTIVOS FIJOS | D196: UND - UNIDAD | E196: 034 - OTRAS COMPRAS CTA | F196: 0 | G196: 19 | H196: 0 | I196: Activo | J196: NO | K196: 0 | L196: 0 | M196: NO | N196: NO | O196: SI | P196: NO | Q196: Cesar Augusto Rolon Cañon | R196: 15/11/2023
A197: 196 | B197: TORRE | C197: N - OTRAS COMPRAS | D197: UND - UNIDAD | E197: 055 - UTILES PAPELERIA Y FOTOCOPIAS CTA | F197: 0 | G197: 19 | H197: 0 | I197: Activo | J197: NO | K197: 0 | L197: 0 | M197: NO | N197: NO | O197: SI | P197: NO | Q197: Cesar Augusto Rolon Cañon | R197: 15/11/2023
A198: 197 | B198: AIO COMPUTADOR | C198: E - ACTIVOS FIJOS | D198: UND - UNIDAD | E198: 034 - OTRAS COMPRAS CTA | F198: 0 | G198: 19 | H198: 0 | I198: Activo | J198: NO | K198: 0 | L198: 0 | M198: NO | N198: NO | O198: SI | P198: NO | Q198: Cesar Augusto Rolon Cañon | R198: 15/11/2023
A199: 198 | B199: MESNITOR | C199: N - OTRAS COMPRAS | D199: UND - UNIDAD | E199: 034 - OTRAS COMPRAS CTA | F199: 0 | G199: 19 | H199: 0 | I199: Activo | J199: NO | K199: 0 | L199: 0 | M199: NO | N199: NO | O199: SI | P199: NO | Q199: Cesar Augusto Rolon Cañon | R199: 15/11/2023
A200: 199 | B200: TECLADO | C200: N - OTRAS COMPRAS | D200: UND - UNIDAD | E200: 034 - OTRAS COMPRAS CTA | F200: 0 | G200: 19 | H200: 0 | I200: Activo | J200: NO | K200: 0 | L200: 0 | M200: NO | N200: NO | O200: SI | P200: NO | Q200: Cesar Augusto Rolon Cañon | R200: 15/11/2023
A201: 200 | B201: MESUSE | C201: N - OTRAS COMPRAS | D201: UND - UNIDAD | E201: 034 - OTRAS COMPRAS CTA | F201: 0 | G201: 19 | H201: 0 | I201: Activo | J201: NO | K201: 0 | L201: 0 | M201: NO | N201: NO | O201: SI | P201: NO | Q201: Cesar Augusto Rolon Cañon | R201: 15/11/2023
A202: 201 | B202: SSD 0 DISCO EN ESTADO SOLIDO | C202: N - OTRAS COMPRAS | D202: UND - UNIDAD | E202: 055 - UTILES PAPELERIA Y FOTOCOPIAS CTA | F202: 0 | G202: 19 | H202: 0 | I202: Activo | J202: NO | K202: 0 | L202: 0 | M202: NO | N202: NO | O202: SI | P202: NO | Q202: Cesar Augusto Rolon Cañon | R202: 15/11/2023
... A208: 207 | B208: MESRRAL | C208: N - OTRAS COMPRAS | D208: UND - UNIDAD | E208: 055 - UTILES PAPELERIA Y FOTOCOPIAS CTA | F208: 0 | G208: 19 | H208: 0 | I208: Activo | J208: NO | K208: 0 | L208: 0 | M208: NO | N208: NO | O208: SI | P208: NO | Q208: Cesar Augusto Rolon Cañon | R208: 15/11/2023
A209: 208 | B209: KIT DE LIMPIEZA INCLUYE SPRAY ALCOHOL ISOPROPILICO Y PAÑO | C209: M - INVENTARIO | D209: UND - UNIDAD | E209: 034 - OTRAS COMPRAS CTA | F209: 48000 | G209: 19 | H209: 57120 | I209: Activo | J209: NO | K209: 0 | L209: 0 | M209: NO | N209: NO | O209: SI | P209: NO | Q209: Cesar Augusto Rolon Cañon | R209: 15/11/2023 | S209: Ruben Dario Villabona Sarmiento | T209: 28/06/2024
A210: 209 | B210: HERRAMINTAS MENORES | C210: N - OTRAS COMPRAS | D210: UND - UNIDAD | E210: 055 - UTILES PAPELERIA Y FOTOCOPIAS CTA | F210: 0 | G210: 19 | H210: 0 | I210: Activo | J210: NO | K210: 0 | L210: 0 | M210: NO | N210: NO | O210: SI | P210: NO | Q210: Cesar Augusto Rolon Cañon | R210: 15/11/2023
A211: 210 | B211: IMPRESORA | C211: N - OTRAS COMPRAS | D211: UND - UNIDAD | E211: 034 - OTRAS COMPRAS CTA | F211: 0 | G211: 19 | H211: 0 | I211: Activo | J211: NO | K211: 0 | L211: 0 | M211: NO | N211: NO | O211: SI | P211: NO | Q211: Cesar Augusto Rolon Cañon | R211: 15/11/2023
A212: 211 | B212: SCANNER | C212: N - OTRAS COMPRAS | D212: UND - UNIDAD | E212: 034 - OTRAS COMPRAS CTA | F212: 0 | G212: 19 | H212: 0 | I212: Activo | J212: NO | K212: 0 | L212: 0 | M212: NO | N212: NO | O212: SI | P212: NO | Q212: Cesar Augusto Rolon Cañon | R212: 15/11/2023
A213: 212 | B213: MULTIPUERTOS | C213: N - OTRAS COMPRAS | D213: UND - UNIDAD | E213: 055 - UTILES PAPELERIA Y FOTOCOPIAS CTA | F213: 0 | G213: 19 | H213: 0 | I213: Activo | J213: NO | K213: 0 | L213: 0 | M213: NO | N213: NO | O213: SI | P213: NO | Q213: Cesar Augusto Rolon Cañon | R213: 15/11/2023
A214: 213 | B214: SERVICIO MIS FACTURAS | C214: B - SOFTWARE | D214: AÑO - AÑO | E214: 031 - LICENCIAS | F214: 0 | G214: 19 | H214: 0 | I214: Activo | J214: NO | K214: 0 | L214: 0 | M214: NO | N214: NO | O214: SI | P214: NO | Q214: Cesar Augusto Rolon Cañon | R214: 15/11/2023
A215: 214 | B215: SERVICIO MESVIL CORPORATIVO | C215: S - SERVICIOS | D215: MES - MES | E215: 053 - TELEFONO | F215: 0 | G215: 19 | H215: 0 | I215: Activo | J215: NO | K215: 0 | L215: 0 | M215: NO | N215: NO | O215: SI | P215: NO | Q215: Cesar Augusto Rolon Cañon | R215: 15/11/2023
A216: 215 | B216: DESTORNILLADORES | C216: N - OTRAS COMPRAS | D216: UND - UNIDAD | E216: 034 - OTRAS COMPRAS CTA | F216: 0 | G216: 19 | H216: 0 | I216: Activo | J216: NO | K216: 0 | L216: 0 | M216: NO | N216: NO | O216: SI | P216: NO | Q216: Cesar Augusto Rolon Cañon | R216: 15/11/2023
A217: 216 | B217: PERILLEROS | C217: N - OTRAS COMPRAS | D217: UND - UNIDAD | E217: 034 - OTRAS COMPRAS CTA | F217: 0 | G217: 19 | H217: 0 | I217: Activo | J217: NO | K217: 0 | L217: 0 | M217: NO | N217: NO | O217: SI | P217: NO | Q217: Cesar Augusto Rolon Cañon | R217: 15/11/2023
A218: 217 | B218: ROUTERS | C218: N - OTRAS COMPRAS | D218: UND - UNIDAD | E218: 034 - OTRAS COMPRAS CTA | F218: 0 | G218: 19 | H218: 0 | I218: Activo | J218: NO | K218: 0 | L218: 0 | M218: NO | N218: NO | O218: SI | P218: NO | Q218: Cesar Augusto Rolon Cañon | R218: 15/11/2023
A219: 218 | B219: CABLE UTP | C219: N - OTRAS COMPRAS | D219: CJ - CAJA | E219: 034 - OTRAS COMPRAS CTA | F219: 0 | G219: 19 | H219: 0 | I219: Activo | J219: NO | K219: 0 | L219: 0 | M219: NO | N219: NO | O219: SI | P219: NO | Q219: Cesar Augusto Rolon Cañon | R219: 15/11/2023
...

Sheet Capítulos
A1: CAPÍTULO | B1: TIPO DE COSTO | C1: DESCRIPCIÓN
A2: ADMINISTRACION | B2: OPEX | C2: Gastos generales de oficina, papelería, servicios públicos, viáticos administrativos.
A3: RECURSOS HUMANOS | B3: OPEX | C3: Nómina, prestaciones sociales, contrataciones, bienestar laboral.
A4: SST | B4: OPEX | C4: Dotación de EPP, capacitaciones en seguridad, exámenes médicos, programas de prevención.
A5: MANTENIMIENTO RUTINARIO | B5: OPEX | C5: Actividades recurrentes como limpieza de cunetas, bacheo menor, corte de césped, señalización.
A6: MANTENIMIENTO MAYOR | B6: CAPEX | C6: Rehabilitaciones de pavimento: intervenciones programadas, no recurrentes que buscan restaurar, rehabilitar o prolongar la vida útil de la infraestructura vial
A7: OPERACION DE VIAS | B7: OPEX | C7: Personal de peajes, sistemas ITS, energía en estaciones, insumos de operación vial.
A8: POLICIA DE CARRETERAS | B8: OPEX | C8: Convenios con la Policía de Carreteras.
A9: INVERSIÓN ACTIVOS | B9: CAPEX | C9: Compra de vehículos, maquinaria, equipos de cómputo, mobiliario o infraestructura nueva.
A10: GESTION AMBIENTAL | B10: OPEX | C10: Monitoreos ambientales, cumplimiento de licencias, planes de manejo ambiental.
A11: GESTION PREDIAL | B11: OPEX | C11: Gastos de la gestión predial que no pasen por la Subcuenta
A12: GESTION SOCIAL | B12: OPEX | C12: Programas de gestión social
... A17: IMPUESTOS | B17: OPEX | C17: Impuestos prediales, ICA, retenciones, industria y comercio, impuestos de vehículos.
A22: SUCURSAL | B22: SUCURSAL ADMINISTRATIVA
A23: Presupuesto 2026 PA | B23: Patrimonio Autónomo
A24: Presupuesto 2026 CTS | B24: Concesion transversal del Sisga
A25: Presupuesto RRHH 2026 | B25: Concesion transversal del Sisga
A26: Obras de Emergencia | B26: OBRAS Menores a Cargo de la ANI

Sheet Presupuesto 2026
B2: Variable
B3: IPC (dic/dic) | C3: 4,0%
B4: Salario mínimo | C4: 0.08
B5: TRM promedio (COP/USD) | C5: $4.250
A7: Capítulo | B7: ítem | C7: Insumo | D7: Descripción | E7: Unidad | F7: Cantidad 2026 | G7: Precio Base 2025 | H7: Precio Base 2026 | I7: Valor Total | J7: Supuestos | K7: Observaciones | L7: Soporte | M7: Total Presupuesto 2026 | N7: Enero | O7: febrero | P7: marzo | Q7: abril | R7: mayo | S7: junio | T7: julio | U7: agosto | V7: septiembre | W7: octubre | X7: noviembre | Y7: diciembre
A8: =Capítulos!$A$2 -> ADMINISTRACION | B8: GASTOS GENERALES OFICINA BOGOTÁ | C8: ARRENDAMIENTO OFICINA | D8: Arrendamiento oficina Teleport 502 | E8: Mes | F8: 12 | G8: 11305000 | H8: =G8*(1+$C$3) -> 11757200 | I8: =+F8*H8 -> 141086400 | J8: Consumo estimado para el año 2026 | K8: precio según contrato | L8: Contrato de Arrendamiento suscrito en 2025 | M8: =SUM(N8:Y8) -> 141086400 | N8: =+I8/$F8 -> 11757200 | O8: =+$I$8/$F$8 -> 11757200 | P8: =+$I$8/$F$8 -> 11757200 | Q8: =+$I$8/$F$8 -> 11757200 | R8: =+$I$8/$F$8 -> 11757200 | S8: =+$I$8/$F$8 -> 11757200 | T8: =+$I$8/$F$8 -> 11757200 | U8: =+$I$8/$F$8 -> 11757200 | V8: =+$I$8/$F$8 -> 11757200 | ... Y8: =+$I$8/$F$8 -> 11757200
A9: =Capítulos!$A$2 -> ADMINISTRACION | B9: GASTOS GENERALES OFICINA BOGOTÁ | C9: ADMINISTRACIÓN OFICINA | D9: Administración oficina Teleport 502 | E9: Mes | F9: 12 | G9: 2258812 | H9: =G9*(1+$C$3) -> 2349164.5 | I9: =+F9*H9 -> 28189974 | J9: Consumo estimado para el año 2026 | K9: precio según contrato | L9: Contrato de Administración suscrito en 2025 | M9: =SUM(N9:Y9) -> 28189974 | N9: =+$I$9/$F$9 -> 2349164.5 | O9: =+$I$9/$F$9 -> 2349164.5 | P9: =+$I$9/$F$9 -> 2349164.5 | Q9: =+$I$9/$F$9 -> 2349164.5 | R9: =+$I$9/$F$9 -> 2349164.5 | S9: =+$I$9/$F$9 -> 2349164.5 | T9: =+$I$9/$F$9 -> 2349164.5 | U9: =+$I$9/$F$9 -> 2349164.5 | ... Y9: =+$I$9/$F$9 -> 2349164.5
A10: =Capítulos!$A$2 -> ADMINISTRACION | B10: GASTOS PAPELERIA OFICINA BOGOTÁ | C10: ALMOHADILLA DACTILAR | D10: Almohadilla X 4000 Huellas | E10: unidad | F10: 10 | G10: 5000 | H10: =G10*(1+$C$3) -> 5200 | I10: =+F10*H10 -> 52000 | J10: Consumo estimado para el año 2026 | K10: Precio promedio de mercado | L10: Cotización | M10: =SUM(N10:Y10) -> 52000 | O10: =+$I$10/3 -> 17333.333 | S10: =+$I$10/3 -> 17333.333 | W10: =+$I$10/3 -> 17333.333
A11: =Capítulos!$A$2 -> ADMINISTRACION | B11: GASTOS PAPELERIA OFICINA BOGOTÁ | C11: AZ CARTA AZUL PLASTIFICADO | D11: AZ para archivo | E11: unidad | F11: 500 | G11: 700 | H11: =G11*(1+$C$3) -> 728 | I11: =+F11*H11 -> 364000 | J11: Consumo estimado para el año 2026 | K11: Precio promedio de mercado | L11: Cotización | M11: =SUM(N11:Y11) -> 364000 | O11: =+$I$11/3 -> 121333.33 | S11: =+$I$11/3 -> 121333.33 | W11: =+$I$11/3 -> 121333.33
A12: =Capítulos!$A$2 -> ADMINISTRACION | B12: GASTOS PAPELERIA OFICINA BOGOTÁ | C12: AZ OFICIO AZUL PLASTIFICADO | D12: AZ para archivo | E12: unidad | F12: 1000 | G12: 800 | H12: =G12*(1+$C$3) -> 832 | I12: =+F12*H12 -> 832000 | J12: Consumo estimado para el año 2026 | K12: Precio promedio de mercado | L12: Cotización | M12: =SUM(N12:Y12) -> 832000 | O12: =+$I$12/3 -> 277333.33 | S12: =+$I$12/3 -> 277333.33 | W12: =+$I$12/3 -> 277333.33
A13: =Capítulos!$A$2 -> ADMINISTRACION | B13: GASTOS PAPELERIA OFICINA BOGOTÁ | C13: BANDERITAS COLORES | D13: Banderitas por 5 unidades paquete | E13: unidad | F13: 10 | G13: 4000 | H13: =G13*(1+$C$3) -> 4160 | I13: =+F13*H13 -> 41600 | J13: Consumo estimado para el año 2026 para las 5 sedes | K13: Precio promedio de mercado | L13: Cotización | M13: =SUM(N13:Y13) -> 41600 | O13: =+$I$13/3 -> 13866.667 | S13: =+$I$13/3 -> 13866.667 | W13: =+$I$13/3 -> 13866.667
A14: =Capítulos!$A$2 -> ADMINISTRACION | B14: GASTOS PAPELERIA OFICINA BOGOTÁ | C14: BISTURI GRANDE PLASTICO | H14: =G14*(1+$C$3) -> 0 | I14: =+F14*H14 -> 0 | M14: =SUM(N14:Y14) -> 0
A15: =Capítulos!$A$2 -> ADMINISTRACION | B15: GASTOS PAPELERIA OFICINA BOGOTÁ | C15: BLOCK AMARILLO MEDIA CARTA CUADRICULADO 50H | H15: =G15*(1+$C$3) -> 0 | I15: =+F15*H15 -> 0 | M15: =SUM(N15:Y15) -> 0
A16: =Capítulos!$A$2 -> ADMINISTRACION | B16: GASTOS PAPELERIA OFICINA BOGOTÁ | C16: BLOCK IRIS CARTA X 35 HOJAS | H16: =G16*(1+$C$3) -> 0 | I16: =+F16*H16 -> 0 | M16: =SUM(N16:Y16) -> 0
A17: =Capítulos!$A$2 -> ADMINISTRACION | B17: GASTOS PAPELERIA OFICINA BOGOTÁ | C17: BLOCK MILIMETRADO OFICIO 25H | H17: =G17*(1+$C$3) -> 0 | I17: =+F17*H17 -> 0 | M17: =SUM(N17:Y17) -> 0
A18: =Capítulos!$A$2 -> ADMINISTRACION | B18: GASTOS PAPELERIA OFICINA BOGOTÁ | C18: BOLSA DE VINILO CARTA DELGADA PAQUETE X 20 UND | H18: =G18*(1+$C$3) -> 0 | I18: =+F18*H18 -> 0 | M18: =SUM(N18:Y18) -> 0
A19: =Capítulos!$A$2 -> ADMINISTRACION | B19: GASTOS GENERALES OFICINA CCO | H19: =G19*(1+$C$3) -> 0 | I19: =+F19*H19 -> 0
A20: =Capítulos!$A$2 -> ADMINISTRACION | B20: GASTOS GENERALES AREA SERVICIOS SLG | H20: =G20*(1+$C$3) -> 0 | I20: =+F20*H20 -> 0
A21: =Capítulos!$A$2 -> ADMINISTRACION | B21: GASTOS GENERALES AREA SERVICIOS MACHETA | H21: =G21*(1+$C$3) -> 0 | I21: =+F21*H21 -> 0
A22: =Capítulos!$A$2 -> ADMINISTRACION | B22: GASTOS GENERALES PEAJE SLG | H22: =G22*(1+$C$3) -> 0 | I22: =+F22*H22 -> 0
A23: =Capítulos!$A$2 -> ADMINISTRACION | B23: GASTOS GENERALES PEAJE MACHETA | H23: =G23*(1+$C$3) -> 0 | I23: =+F23*H23 -> 0
A24: =Capítulos!$A$2 -> ADMINISTRACION | B24: BAÑOS MOVILES | H24: =G24*(1+$C$3) -> 0 | I24: =+F24*H24 -> 0
A25: =Capítulos!$A$2 -> ADMINISTRACION | B25: ASESORIAS Y AFILIACIONES | H25: =G25*(1+$C$3) -> 0 | I25: =+F25*H25 -> 0
A26: =Capítulos!A4 -> SST | B26: DOTACION | C26: CAMISAS MUJER BLANCA TALLA XS | H26: =G26*(1+$C$3) -> 0 | I26: =+F26*H26 -> 0
A27: SST | B27: DOTACION | C27: CAMISAS MUJER BLANCA TALLA S | H27: =G27*(1+$C$3) -> 0 | I27: =+F27*H27 -> 0
A28: SST | B28: DOTACION | C28: CAMISAS HOMBRE BLANCAS TALLA L | H28: =G28*(1+$C$3) -> 0 | I28: =+F28*H28 -> 0
A29: SST | B29: DOTACION | C29: CAMISAS HOMBRE BLANCAS TALLA XL | H29: =G29*(1+$C$3) -> 0 | I29: =+F29*H29 -> 0
A30: SST | B30: DOTACION | C30: CAMISAS HOMBRE AZUL TALLA L 0 CONSERJE | H30: =G30*(1+$C$3) -> 0 | I30: =+F30*H30 -> 0
A31: SST | B31: DOTACION | C31: CAMISAS HOMBRE AZUL TALLA XL 0 CONSERJE | H31: =G31*(1+$C$3) -> 0 | I31: =+F31*H31 -> 0
A32: SST | B32: DOTACION | C32: PANTALÓN JEANS MUJER TALLA 10 | H32: =G32*(1+$C$3) -> 0 | I32: =+F32*H32 -> 0
A33: SST | B33: DOTACION | C33: PANTALÓN JEANS MUJER TALLA 12 | H33: =G33*(1+$C$3) -> 0 | I33: =+F33*H33 -> 0
A34: SST | B34: DOTACION | C34: PANTALÓN JEANS HOMBRE TALLA 40 | H34: =G34*(1+$C$3) -> 0 | I34: =+F34*H34 -> 0
A35: SST | B35: DOTACION | C35: PANTALÓN JEANS HOMBRE TALLA 42 | H35: =G35*(1+$C$3) -> 0 | I35: =+F35*H35 -> 0
A36: SST | B36: DOTACION | C36: CHAQUETA TALLA XL DAMA | H36: =G36*(1+$C$3) -> 0 | I36: =+F36*H36 -> 0
A37: SST | B37: DOTACION | C37: CHAQUETA TALLA XXL HOMBRE | H37: =G37*(1+$C$3) -> 0 | I37: =+F37*H37 -> 0
A38: SST | B38: DOTACION | C38: CONJUNTO ANTIFLUIDO TALLA S | H38: =G38*(1+$C$3) -> 0 | I38: =+F38*H38 -> 0
... A48: MANTENIMIENTO RUTINARIO | B48: PINTURA | C48: PINTURA TERTRAFICO ACRILICO BASE SOLVENTE BLANCO | H48: =G48*(1+$C$3) -> 0 | I48: =+F48*H48 -> 0
A49: MANTENIMIENTO RUTINARIO | B49: PINTURA | C49: MICROESFERA DE VIDRIO TIPO I SWARCO BULTO X 25KG | E49: Bulto | F49: 20 | G49: 1000000 | H49: =G49*(1+$C$3) -> 1040000 | I49: =+H49*F49 -> 20800000 | J49: Demarcación del PR XXX al PR XXX TODAS LAS UF | K49: Precio promedio de mercado, sujeto a ajuste.
A50: MANTENIMIENTO RUTINARIO | B50: TACHAS | C50: TACHA BIDIRECCIONAL CON ESPIGO BLANCA / ROJA | H50: =G50*(1+$C$3) -> 0
A51: MANTENIMIENTO RUTINARIO | B51: TACHAS | C51: TACHA BIDIRECCIONAL CON ESPIGO AMARILLA | H51: =G51*(1+$C$3) -> 0
A52: MANTENIMIENTO RUTINARIO | B52: TACHAS | C52: TACHAS EN ALUMINIO SOLAR CON ESPIGO COLOR ROJO/ROJO | H52: =G52*(1+$C$3) -> 0
A53: MANTENIMIENTO RUTINARIO | B53: AVISOS & DEFENSAS | H53: =G53*(1+$C$3) -> 0
A54: MANTENIMIENTO RUTINARIO | B54: CUNETAS Y MUROS | H54: =G54*(1+$C$3) -> 0
A55: MANTENIMIENTO RUTINARIO | B55: LIMPIEZA DA ALCANTARILLAS Y BOXCOULVERT | H55: =G55*(1+$C$3) -> 0
A56: MANTENIMIENTO RUTINARIO | B56: MANTENIMIENTO DE TALUDES | H56: =G56*(1+$C$3) -> 0
A57: MANTENIMIENTO RUTINARIO | B57: MANTENIMIENTO DE PUENTES | H57: =G57*(1+$C$3) -> 0
A58: MANTENIMIENTO RUTINARIO | B58: ROCERIA | H58: =G58*(1+$C$3) -> 0
A59: MANTENIMIENTO RUTINARIO | B59: BACHEO | C59: MEZCLA DENSA MDC0190 | D59: Mezcla densa en caliente | E59: m³ | F59: 619 | G59: 635536.78 | H59: =G59*(1+$C$3) -> 660958.25 | I59: 3.9339727e+08 | J59: Consumo estimado en pavimentación UF2, frente PR40+200. | K59: Precio según última compra 2025.
A60: MANTENIMIENTO RUTINARIO | B60: BACHEO | C60: SERVICIO INSTALACIÓN DE MEZCLA DENSA EN CALIENTE | D60: Servicio | E60: m³ | F60: 619 | G60: 800000 | H60: =G60*(1+$C$3) -> 832000 | I60: 3.9339727e+08
A61: MANTENIMIENTO MAYOR
A62: OPERACION DE VIAS
A63: POLICIA DE CARRETERAS
A64: INVERSIÓN ACTIVOS
A65: GESTION AMBIENTAL
A66: GESTION PREDIAL
A67: GESTION SOCIAL
A68: JURIDICA
A69: POLIZAS
A70: FINANCIERA
A71: FONDEOS
A72: IMPUESTOS

Sheet Mto Rutinario
B2: Variable
B3: IPC (dic/dic) | C3: 4,0%
B4: Salario mínimo | C4: 0.08
B5: TRM promedio (COP/USD) | C5: $4.250
A7: Capítulo | B7: ítem | C7: Insumo | D7: Descripción | E7: Unidad | F7: Cantidad 2026 | G7: Precio Base 2025 | H7: Precio Base 2026 | I7: Valor Total | J7: Supuestos | K7: Observaciones | L7: Soporte | M7: Total Presupuesto 2026 | N7: Enero | O7: febrero | P7: marzo | Q7: abril | R7: mayo | S7: junio | T7: julio | U7: agosto | V7: septiembre | W7: octubre | X7: noviembre | Y7: diciembre
A8: MANTENIMIENTO RUTINARIO | B8: PINTURA | C8: PINTURA TERTRAFICO ACRILICO BASE SOLVENTE AMARILLO | H8: =G8*(1+$C$3) -> 0 | I8: =+F8*H8 -> 0
A9: MANTENIMIENTO RUTINARIO | B9: PINTURA | C9: PINTURA TERTRAFICO ACRILICO BASE SOLVENTE BLANCO | H9: =G9*(1+$C$3) -> 0 | I9: =+F9*H9 -> 0
A10: MANTENIMIENTO RUTINARIO | B10: PINTURA | C10: MICROESFERA DE VIDRIO TIPO I SWARCO BULTO X 25KG | E10: Bulto | F10: 20 | G10: 1000000 | H10: =G10*(1+$C$3) -> 1040000 | I10: =+H10*F10 -> 20800000 | J10: Demarcación del PR XXX al PR XXX TODAS LAS UF | K10: Precio promedio de mercado, sujeto a ajuste.
A11: MANTENIMIENTO RUTINARIO | B11: TACHAS | C11: TACHA BIDIRECCIONAL CON ESPIGO BLANCA / ROJA | H11: =G11*(1+$C$3) -> 0
A12: MANTENIMIENTO RUTINARIO | B12: TACHAS | C12: TACHA BIDIRECCIONAL CON ESPIGO AMARILLA | H12: =G12*(1+$C$3) -> 0
A13: MANTENIMIENTO RUTINARIO | B13: TACHAS | C13: TACHAS EN ALUMINIO SOLAR CON ESPIGO COLOR ROJO/ROJO | H13: =G13*(1+$C$3) -> 0
A14: MANTENIMIENTO RUTINARIO | B14: AVISOS & DEFENSAS | H14: =G14*(1+$C$3) -> 0
A15: MANTENIMIENTO RUTINARIO | B15: CUNETAS Y MUROS | H15: =G15*(1+$C$3) -> 0
A16: MANTENIMIENTO RUTINARIO | B16: LIMPIEZA DA ALCANTARILLAS Y BOXCOULVERT | H16: =G16*(1+$C$3) -> 0
A17: MANTENIMIENTO RUTINARIO | B17: MANTENIMIENTO DE TALUDES | H17: =G17*(1+$C$3) -> 0
A18: MANTENIMIENTO RUTINARIO | B18: MANTENIMIENTO DE PUENTES | H18: =G18*(1+$C$3) -> 0
A19: MANTENIMIENTO RUTINARIO | B19: ROCERIA | H19: =G19*(1+$C$3) -> 0
A20: MANTENIMIENTO RUTINARIO | B20: BACHEO | C20: MEZCLA DENSA MDC0190 | D20: Mezcla densa en caliente | E20: m³ | F20: 619 | G20: 635536.78 | H20: =G20*(1+$C$3) -> 660958.25 | I20: 3.9339727e+08 | J20: Consumo estimado en pavimentación UF2, frente PR40+200. | K20: Precio según última compra 2025.
A21: MANTENIMIENTO RUTINARIO | B21: BACHEO | C21: SERVICIO INSTALACIÓN DE MEZCLA DENSA EN CALIENTE | D21: Servicio | E21: m³ | F21: 619 | G21: 800000 | H21: =G21*(1+$C$3) -> 832000 | I21: 3.9339727e+08

Sheet Mto Periódico
B2: Variable
B3: IPC (dic/dic) | C3: 4,0%
B4: Salario mínimo | C4: 0.08
B5: TRM promedio (COP/USD) | C5: $4.250
A7: Capítulo | B7: ítem | C7: Insumo | D7: Descripción | E7: Unidad | F7: Cantidad 2026 | G7: Precio Base 2025 | H7: Precio Base 2026 | I7: Valor Total | J7: Supuestos | K7: Observaciones | L7: Soporte | M7: Total Presupuesto 2026 | N7: Enero | O7: febrero | P7: marzo | Q7: abril | R7: mayo | S7: junio | T7: julio | U7: agosto | V7: septiembre | W7: octubre | X7: noviembre | Y7: diciembre
A8: MANTENIMIENTO MAYOR

Sheet Operación Vías
B2: Variable
B3: IPC (dic/dic) | C3: 0.051
B4: Salario mínimo | C4: 0.23
B5: TRM promedio (COP/USD) | C5: $4.250
A7: Capítulo | B7: ítem | C7: Insumo | D7: Descripción | E7: Unidad | F7: Cantidad 2026 | G7: Precio Base 2025 | H7: Precio Base 2026 | I7: Valor Total | J7: Supuestos | K7: Observaciones | L7: Soporte | M7: Total Presupuesto 2026 | N7: Enero | O7: febrero | P7: marzo | Q7: abril | R7: mayo | S7: junio | T7: julio | U7: agosto | V7: septiembre | W7: octubre | X7: noviembre | Y7: diciembre
A8: OPERACION DE VIAS | B8: OPERACION PEAJES | C8: OPERACION INTEGRAL ESTACIÓN DE PEAJE MACHETA | M8: =SUM(N8:Y8) -> 2.1969934e+09 | N8: =SUM(N9:N21) -> 1.9851884e+08 | O8: =SUM(O9:O21) -> 1.7971732e+08 | P8: =SUM(P9:P21) -> 1.7925955e+08 | Q8: =SUM(Q9:Q21) -> 1.7925955e+08 | R8: =SUM(R9:R21) -> 1.8097049e+08 | S8: =SUM(S9:S21) -> 1.7925955e+08 | T8: =SUM(T9:T21) -> 1.8195536e+08 | U8: =SUM(U9:U21) -> 1.8092584e+08 | ... Y8: =SUM(Y9:Y21) -> 1.8503092e+08
A9: OPERACION DE VIAS | B9: OPERACION PEAJES | C9: OPERACION INTEGRAL ESTACIÓN DE PEAJE MACHETA | D9: SERVICIO OPERACIÓN PEAJE | E9: MENSUAL | F9: 12 | G9: 126398293 | H9: =G9*(1+C$4) -> 1.554699e+08 | I9: =H9*F9 -> 1.8656388e+09 | M9: =SUM(N9:Y9) -> 1.8656388e+09 | N9: =H9 -> 1.554699e+08 | O9: =+N9 -> 1.554699e+08 | P9: =+O9 -> 1.554699e+08 | Q9: =+P9 -> 1.554699e+08 | R9: =+Q9 -> 1.554699e+08 | S9: =+R9 -> 1.554699e+08 | T9: =+S9 -> 1.554699e+08 | U9: =+T9 -> 1.554699e+08 | V9: =+U9 -> 1.554699e+08 | ... Y9: =+X9 -> 1.554699e+08
A10: OPERACION DE VIAS | B10: OPERACION PEAJES | C10: OPERACION INTEGRAL ESTACIÓN DE PEAJE MACHETA | D10: SERVICIO RECAUDADORES APOYO | E10: MENSUAL | F10: 3 | G10: =14076524/3 -> 4692174.7 | H10: =G10*(1+C$4) -> 5771374.8 | I10: =H10*F10 -> 17314125 | M10: =SUM(N10:Y10) -> 17314125 | N10: 0 | O10: 0 | P10: 0 | Q10: 0 | R10: 0 | S10: 0 | T10: 0 | U10: 0 | V10: 0 | W10: =H10 -> 5771374.8 | X10: =W10 -> 5771374.8 | Y10: =X10 -> 5771374.8
A11: OPERACION DE VIAS | B11: OPERACION PEAJES | C11: OPERACION INTEGRAL ESTACIÓN DE PEAJE MACHETA | D11: SERVICIO ALQUILER DATAFONOS | E11: MENSUAL | F11: 12 | G11: =69000*2 -> 138000 | H11: =G11*(1+C$3) -> 145038 | I11: =H11*13 -> 1885494 | M11: =SUM(N11:Y11) -> 1885494 | N11: =H11*2 -> 290076 | O11: =H11 -> 145038 | P11: =+O11 -> 145038 | Q11: =+P11 -> 145038 | R11: =+Q11 -> 145038 | S11: =+R11 -> 145038 | T11: =+S11 -> 145038 | U11: =+T11 -> 145038 | V11: =+U11 -> 145038 | W11: =+V11 -> 145038 | ... Y11: =+X11 -> 145038
A12: OPERACION DE VIAS | B12: OPERACION PEAJES | C12: OPERACION INTEGRAL ESTACIÓN DE PEAJE MACHETA | D12: SERVICIO INTEROPERABILIDAD IP/REV | E12: MENSUAL | F12: 12 | G12: 15601887 | H12: =G12*(1+C$3) -> 16397583 | I12: =H12*13 -> 2.1316858e+08 | M12: =SUM(N12:Y12) -> 2.1316858e+08 | N12: =H12*2 -> 32795167 | O12: =H12 -> 16397583 | P12: =O12 -> 16397583 | Q12: =P12 -> 16397583 | R12: =Q12 -> 16397583 | S12: =R12 -> 16397583 | T12: =S12 -> 16397583 | U12: =T12 -> 16397583 | V12: =U12 -> 16397583 | W12: =V12 -> 16397583 | ... Y12: =X12 -> 16397583
A13: OPERACION DE VIAS | B13: OPERACION PEAJES | C13: OPERACION INTEGRAL ESTACIÓN DE PEAJE MACHETA | D13: SERVICIO MTTO SOFTWARE RECAUDO | E13: MENSUAL | F13: 12 | G13: 4171283 | H13: =G13*(1+C$4) -> 5130678.1 | I13: =H13*F13 -> 61568137 | M13: =SUM(N13:Y13) -> 61568137 | N13: =H13 -> 5130678.1 | O13: =+N13 -> 5130678.1 | P13: =+O13 -> 5130678.1 | Q13: =+P13 -> 5130678.1 | R13: =+Q13 -> 5130678.1 | S13: =+R13 -> 5130678.1 | T13: =+S13 -> 5130678.1 | U13: =+T13 -> 5130678.1 | V13: =+U13 -> 5130678.1 | ... Y13: =+X13 -> 5130678.1
A14: OPERACION DE VIAS | B14: OPERACION PEAJES | C14: OPERACION INTEGRAL ESTACIÓN DE PEAJE MACHETA | D14: SERVICIO EMISIÓN DEE | E14: MENSUAL | F14: 12 | G14: =23*87550 -> 2013650 | H14: =G14*(1+C$3) -> 2116346.1 | I14: =H14*13 -> 27512500 | M14: =SUM(N14:Y14) -> 27512500 | N14: =H14*2 -> 4232692.3 | O14: =H14 -> 2116346.1 | P14: =+O14 -> 2116346.1 | Q14: =+P14 -> 2116346.1 | R14: =+Q14 -> 2116346.1 | S14: =+R14 -> 2116346.1 | T14: =+S14 -> 2116346.1 | U14: =+T14 -> 2116346.1 | V14: =+U14 -> 2116346.1 | W14: =+V14 -> 2116346.1 | ... Y14: =+X14 -> 2116346.1
A15: OPERACION DE VIAS | B15: OPERACION PEAJES | C15: OPERACION INTEGRAL ESTACIÓN DE PEAJE MACHETA | D15: STICKER VALLAS TARIFARIAS | E15: UNIDAD | F15: 2 | G15: 285600 | H15: =G15*(1+C$3) -> 300165.6 | I15: =H15*F15 -> 600331.2 | M15: =SUM(N15:Y15) -> 600331.2 | N15: =H15*2 -> 600331.2 | O15: 0 | P15: 0 | Q15: 0 | R15: 0 | S15: 0 | T15: 0 | U15: 0 | V15: 0 | W15: 0 | X15: 0 | Y15: 0
A16: OPERACION DE VIAS | B16: OPERACION PEAJES | C16: OPERACION INTEGRAL ESTACIÓN DE PEAJE MACHETA | D16: BOLETERIA CONTINGENCIA | E16: UNIDAD | F16: 15000 | G16: =171 -> 171 | H16: =G16*(1+C$3) -> 179.721 | I16: =+H16*F16 -> 2695815 | M16: =SUM(N16:Y16) -> 2695815 | N16: 0 | O16: 0 | P16: 0 | Q16: 0 | R16: 0 | S16: 0 | T16: =+H16*F16 -> 2695815 | U16: 0 | V16: 0 | W16: 0 | X16: 0 | Y16: 0
A17: OPERACION DE VIAS | B17: OPERACION PEAJES | C17: OPERACION INTEGRAL ESTACIÓN DE PEAJE MACHETA | D17: CINTA CONSPICUITI | E17: ROLLO | F17: 4 | G17: 406980 | H17: =G17*(1+C$3) -> 427735.98 | I17: =+H17*F17 -> 1710943.9 | M17: =SUM(N17:Y17) -> 1710943.9 | N17: 0 | O17: 0 | P17: 0 | Q17: 0 | R17: =H17*F17 -> 1710943.9 | S17: 0 | T17: 0 | U17: 0 | V17: 0 | W17: 0 | X17: 0 | Y17: 0
A18: OPERACION DE VIAS | B18: OPERACION PEAJES | C18: OPERACION INTEGRAL ESTACIÓN DE PEAJE MACHETA | D18: CONOS 90 CM | E18: UNIDAD | F18: 30 | G18: 88000 | H18: =G18*(1+C$3) -> 92488 | I18: =+H18*F18 -> 2774640 | M18: =SUM(N18:Y18) -> 2774640 | N18: 0 | O18: 0 | P18: 0 | Q18: 0 | R18: 0 | S18: 0 | T18: 0 | U18: 0 | V18: =H18*F18 -> 2774640 | W18: 0 | X18: 0 | Y18: 0
A19: OPERACION DE VIAS | B19: OPERACION PEAJES | C19: OPERACION INTEGRAL ESTACIÓN DE PEAJE MACHETA | D19: PALETAS PARE - SIGA | E19: UNIDAD | F19: 2 | G19: 41067 | H19: =G19*(1+C$3) -> 43161.417 | I19: =+H19*F19 -> 86322.834 | M19: =SUM(N19:Y19) -> 86322.834 | N19: 0 | O19: =H19*F19 -> 86322.834 | P19: 0 | Q19: 0 | R19: 0 | S19: 0 | T19: 0 | U19: 0 | V19: 0 | W19: 0 | X19: 0 | Y19: 0
A20: OPERACION DE VIAS | B20: OPERACION PEAJES | C20: OPERACION INTEGRAL ESTACIÓN DE PEAJE MACHETA | D20: FLASHER SOLAR | E20: UNIDAD | F20: 30 | G20: 41067 | H20: =G20*(1+C$3) -> 43161.417 | I20: =+H20*F20 -> 1294842.5 | M20: =SUM(N20:Y20) -> 1294842.5 | N20: 0 | O20: 0 | P20: 0 | Q20: 0 | R20: 0 | S20: 0 | T20: 0 | U20: =H20*F20 -> 1294842.5 | V20: 0 | W20: 0 | X20: 0 | Y20: 0
A21: OPERACION DE VIAS | B21: OPERACION PEAJES | C21: OPERACION INTEGRAL ESTACIÓN DE PEAJE MACHETA | D21: TALANQUERAS | E21: UNIDAD | F21: 3 | G21: 235620 | H21: =G21*(1+C$3) -> 247636.62 | I21: =+H21*F21 -> 742909.86 | M21: =SUM(N21:Y21) -> 742909.86 | N21: 0 | O21: =H21*F21/2 -> 371454.93 | P21: 0 | Q21: 0 | R21: 0 | S21: 0 | T21: 0 | U21: =O21 -> 371454.93 | V21: 0 | W21: 0 | X21: 0 | Y21: 0
A22: OPERACION DE VIAS | B22: OPERACION PEAJES | C22: OPERACION INTEGRAL ESTACIÓN DE PEAJE SAN LUIS DE GACENO | M22: =SUM(N22:Y22) -> 2.1005054e+09 | N22: =SUM(N23:N35) -> 1.9099262e+08 | O22: =SUM(O23:O35) -> 1.7338887e+08 | P22: =SUM(P23:P35) -> 1.729311e+08 | Q22: =SUM(Q23:Q35) -> 1.729311e+08 | R22: =SUM(R23:R35) -> 1.7464204e+08 | S22: =SUM(S23:S35) -> 1.729311e+08 | T22: =SUM(T23:T35) -> 1.7562691e+08 | U22: =SUM(U23:U35) -> 1.7394997e+08 | ... Y22: =SUM(Y23:Y35) -> 1.729311e+08
A23: OPERACION DE VIAS | B23: OPERACION PEAJES | C23: OPERACION INTEGRAL ESTACIÓN DE PEAJE SAN LUIS DE GACENO | D23: SERVICIO OPERACIÓN PEAJE | E23: MENSUAL | F23: 12 | G23: 126398293 | H23: =G23*(1+C$4) -> 1.554699e+08 | I23: =H23*F23 -> 1.8656388e+09 | M23: =SUM(N23:Y23) -> 1.8656388e+09 | N23: =H23 -> 1.554699e+08 | O23: =+N23 -> 1.554699e+08 | P23: =+O23 -> 1.554699e+08 | Q23: =+P23 -> 1.554699e+08 | R23: =+Q23 -> 1.554699e+08 | S23: =+R23 -> 1.554699e+08 | T23: =+S23 -> 1.554699e+08 | U23: =+T23 -> 1.554699e+08 | V23: =+U23 -> 1.554699e+08 | ... Y23: =+X23 -> 1.554699e+08
A24: OPERACION DE VIAS | B24: OPERACION PEAJES | C24: OPERACION INTEGRAL ESTACIÓN DE PEAJE SAN LUIS DE GACENO | D24: SERVICIO RECAUDADORES APOYO | E24: MENSUAL | F24: 0 | G24: =14076524/3 -> 4692174.7 | H24: =G24*(1+C$4) -> 5771374.8 | I24: =H24*F24 -> 0 | M24: =SUM(N24:Y24) -> 0 | N24: 0 | O24: 0 | P24: 0 | Q24: 0 | R24: 0 | S24: 0 | T24: 0 | U24: 0 | V24: 0 | W24: 0 | X24: =W24 -> 0 | Y24: =X24 -> 0
A25: OPERACION DE VIAS | B25: OPERACION PEAJES | C25: OPERACION INTEGRAL ESTACIÓN DE PEAJE SAN LUIS DE GACENO | D25: SERIVICIO ALQUILER DATAFONOS | E25: MENSUAL | F25: 12 | G25: =69000*2 -> 138000 | H25: =G25*(1+C$3) -> 145038 | I25: =H25*13 -> 1885494 | M25: =SUM(N25:Y25) -> 1885494 | N25: =H25*2 -> 290076 | O25: =H25 -> 145038 | P25: =+O25 -> 145038 | Q25: =+P25 -> 145038 | R25: =+Q25 -> 145038 | S25: =+R25 -> 145038 | T25: =+S25 -> 145038 | U25: =+T25 -> 145038 | V25: =+U25 -> 145038 | W25: =+V25 -> 145038 | ... Y25: =+X25 -> 145038
A26: OPERACION DE VIAS | B26: OPERACION PEAJES | C26: OPERACION INTEGRAL ESTACIÓN DE PEAJE SAN LUIS DE GACENO | D26: SERVICIO INTEROPERABILIDAD IP/REV | E26: MENSUAL | F26: 12 | G26: 15601887 | H26: =G26*(1+C$3) -> 16397583 | I26: =H26*13 -> 2.1316858e+08 | M26: =SUM(N26:Y26) -> 2.1316858e+08 | N26: =H26*2 -> 32795167 | O26: =H26 -> 16397583 | P26: =O26 -> 16397583 | Q26: =P26 -> 16397583 | R26: =Q26 -> 16397583 | S26: =R26 -> 16397583 | T26: =S26 -> 16397583 | U26: =T26 -> 16397583 | V26: =U26 -> 16397583 | W26: =V26 -> 16397583 | ... Y26: =X26 -> 16397583
A27: OPERACION DE VIAS | B27: OPERACION PEAJES | C27: OPERACION INTEGRAL ESTACIÓN DE PEAJE SAN LUIS DE GACENO | D27: SERVICIO MTTO SOFTWARE RECAUDO | E27: MENSUAL | F27: 0 | G27: 4171283 | H27: =G27*(1+C$4) -> 5130678.1 | I27: =H27*F27 -> 0 | M27: =SUM(N27:Y27) -> 0 | N27: 0 | O27: =+N27 -> 0 | P27: =+O27 -> 0 | Q27: =+P27 -> 0 | R27: =+Q27 -> 0 | S27: =+R27 -> 0 | T27: =+S27 -> 0 | U27: =+T27 -> 0 | V27: =+U27 -> 0 | ... Y27: =+X27 -> 0
A28: OPERACION DE VIAS | B28: OPERACION PEAJES | C28: OPERACION INTEGRAL ESTACIÓN DE PEAJE SAN LUIS DE GACENO | D28: SERVICIO EMISIÓN DEE | E28: MENSUAL | F28: 12 | G28: =23*38000 -> 874000 | H28: =G28*(1+C$3) -> 918574 | I28: =H28*13 -> 11941462 | M28: =SUM(N28:Y28) -> 11941462 | N28: =H28*2 -> 1837148 | O28: =H28 -> 918574 | P28: =+O28 -> 918574 | Q28: =+P28 -> 918574 | R28: =+Q28 -> 918574 | S28: =+R28 -> 918574 | T28: =+S28 -> 918574 | U28: =+T28 -> 918574 | V28: =+U28 -> 918574 | W28: =+V28 -> 918574 | ... Y28: =+X28 -> 918574
A29: OPERACION DE VIAS | B29: OPERACION PEAJES | C29: OPERACION INTEGRAL ESTACIÓN DE PEAJE SAN LUIS DE GACENO | D29: STICKER VALLAS TARIFARIAS | E29: UNIDAD | F29: 2 | G29: 285600 | H29: =G29*(1+C$3) -> 300165.6 | I29: =H29*F29 -> 600331.2 | M29: =SUM(N29:Y29) -> 600331.2 | N29: =H29*2 -> 600331.2 | O29: 0 | P29: 0 | Q29: 0 | R29: 0 | S29: 0 | T29: 0 | U29: 0 | V29: 0 | W29: 0 | X29: 0 | Y29: 0
A30: OPERACION DE VIAS | B30: OPERACION PEAJES | C30: OPERACION INTEGRAL ESTACIÓN DE PEAJE SAN LUIS DE GACENO | D30: BOLETERIA CONTINGENCIA | E30: UNIDAD | F30: 15000 | G30: =171 -> 171 | H30: =G30*(1+C$3) -> 179.721 | I30: =+H30*F30 -> 2695815 | M30: =SUM(N30:Y30) -> 2695815 | N30: 0 | O30: 0 | P30: 0 | Q30: 0 | R30: 0 | S30: 0 | T30: =+H30*F30 -> 2695815 | U30: 0 | V30: 0 | W30: 0 | X30: 0 | Y30: 0
A31: OPERACION DE VIAS | B31: OPERACION PEAJES | C31: OPERACION INTEGRAL ESTACIÓN DE PEAJE SAN LUIS DE GACENO | D31: CINTA CONSPICUITI | E31: ROLLO | F31: 4 | G31: 406980 | H31: =G31*(1+C$3) -> 427735.98 | I31: =+H31*F31 -> 1710943.9 | M31: =SUM(N31:Y31) -> 1710943.9 | N31: 0 | O31: 0 | P31: 0 | Q31: 0 | R31: =H31*F31 -> 1710943.9 | S31: 0 | T31: 0 | U31: 0 | V31: 0 | W31: 0 | X31: 0 | Y31: 0
A32: OPERACION DE VIAS | B32: OPERACION PEAJES | C32: OPERACION INTEGRAL ESTACIÓN DE PEAJE SAN LUIS DE GACENO | D32: CONOS 90 CM | E32: UNIDAD | F32: 15 | G32: 88000 | H32: =G32*(1+C$3) -> 92488 | I32: =+H32*F32 -> 1387320 | M32: =SUM(N32:Y32) -> 1387320 | N32: 0 | O32: 0 | P32: 0 | Q32: 0 | R32: 0 | S32: 0 | T32: 0 | U32: 0 | V32: =H32*F32 -> 1387320 | W32: 0 | X32: 0 | Y32: 0
A33: OPERACION DE VIAS | B33: OPERACION PEAJES | C33: OPERACION INTEGRAL ESTACIÓN DE PEAJE SAN LUIS DE GACENO | D33: PALETAS PARE - SIGA | E33: UNIDAD | F33: 2 | G33: 41067 | H33: =G33*(1+C$3) -> 43161.417 | I33: =+H33*F33 -> 86322.834 | M33: =SUM(N33:Y33) -> 86322.834 | N33: 0 | O33: =H33*F33 -> 86322.834 | P33: 0 | Q33: 0 | R33: 0 | S33: 0 | T33: 0 | U33: 0 | V33: 0 | W33: 0 | X33: 0 | Y33: 0
A34: OPERACION DE VIAS | B34: OPERACION PEAJES | C34: OPERACION INTEGRAL ESTACIÓN DE PEAJE SAN LUIS DE GACENO | D34: FLASHER SOLAR | E34: UNIDAD | F34: 15 | G34: 41067 | H34: =G34*(1+C$3) -> 43161.417 | I34: =+H34*F34 -> 647421.25 | M34: =SUM(N34:Y34) -> 647421.25 | N34: 0 | O34: 0 | P34: 0 | Q34: 0 | R34: 0 | S34: 0 | T34: 0 | U34: =H34*F34 -> 647421.25 | V34: 0 | W34: 0 | X34: 0 | Y34: 0
A35: OPERACION DE VIAS | B35: OPERACION PEAJES | C35: OPERACION INTEGRAL ESTACIÓN DE PEAJE SAN LUIS DE GACENO | D35: TALANQUERAS | E35: UNIDAD | F35: 3 | G35: 235620 | H35: =G35*(1+C$3) -> 247636.62 | I35: =+H35*F35 -> 742909.86 | M35: =SUM(N35:Y35) -> 742909.86 | N35: 0 | O35: =H35*F35/2 -> 371454.93 | P35: 0 | Q35: 0 | R35: 0 | S35: 0 | T35: 0 | U35: =O35 -> 371454.93 | V35: 0 | W35: 0 | X35: 0 | Y35: 0
A36: OPERACION DE VIAS | B36: OPERACION PESAJES | C36: OPERACION ESTACIÓN DE PESAJE MACHETA | M36: =SUM(M37:M46) -> 75327505 | N36: =SUM(N37:N46) -> 0 | O36: =SUM(O37:O46) -> 500939.18 | P36: =SUM(P37:P46) -> 27769036 | Q36: =SUM(Q37:Q46) -> 0 | R36: =SUM(R37:R46) -> 13783802 | S36: =SUM(S37:S46) -> 0 | T36: =SUM(T37:T46) -> 0 | ... Y36: =SUM(Y37:Y46) -> 0
A37: OPERACION DE VIAS | B37: OPERACION PESAJES | C37: OPERACION ESTACIÓN DE PESAJE MACHETA | D37: SERVICIO CALIBRACIÓN METROLOGICA | E37: UNIDAD | F37: 1 | G37: 14000571 | H37: =G37*(1+C$3) -> 14714600 | I37: =H37*F37 -> 14714600 | M37: =SUM(N37:Y37) -> 14714600 | N37: 0 | O37: =+N37 -> 0 | P37: 0 | Q37: 0 | R37: 0 | S37: 0 | T37: 0 | U37: 0 | V37: 0 | W37: =I37 -> 14714600 | X37: 0 | Y37: 0
A38: OPERACION DE VIAS | B38: OPERACION PESAJES | C38: OPERACION ESTACIÓN DE PESAJE MACHETA | D38: SERVICIO VERIFICACIÓN SIC | E38: UNIDAD | F38: 1 | G38: 13433102 | H38: =G38*(1+C$3) -> 14118190 | I38: =H38*F38 -> 14118190 | M38: =SUM(N38:Y38) -> 14118190 | N38: 0 | O38: 0 | P38: 0 | Q38: 0 | R38: 0 | S38: 0 | T38: 0 | U38: 0 | V38: 0 | W38: 0 | X38: =I38 -> 14118190 | Y38: 0
A39: OPERACION DE VIAS | B39: OPERACION PESAJES | C39: OPERACION ESTACIÓN DE PESAJE MACHETA | D39: SERVICIO ACTUALIZACIÓN BASCAM | E39: UNIDAD | F39: 1 | G39: 11894000 | H39: =G39*(1+C$3) -> 12500594 | I39: =H39*F39 -> 12500594 | M39: =SUM(N39:Y39) -> 12500594 | N39: 0 | O39: 0 | P39: 0 | Q39: 0 | R39: =I39 -> 12500594 | S39: 0 | T39: 0 | U39: 0 | V39: 0 | W39: 0 | X39: 0 | Y39: 0
A40: OPERACION DE VIAS | B40: OPERACION PESAJES | C40: OPERACION ESTACIÓN DE PESAJE MACHETA | D40: SERVICIO MTTO PREVENTIVO ESTATICA | E40: UNIDAD | F40: 1 | G40: 2921538 | H40: =G40*(1+C$3) -> 3070536.4 | I40: =H40*F40 -> 3070536.4 | M40: =SUM(N40:Y40) -> 3070536.4 | N40: 0 | O40: 0 | P40: =H40 -> 3070536.4 | Q40: 0 | R40: 0 | S40: 0 | T40: 0 | U40: 0 | V40: 0 | W40: 0 | X40: 0 | Y40: 0
A41: OPERACION DE VIAS | B41: OPERACION PESAJES | C41: OPERACION ESTACIÓN DE PESAJE MACHETA | D41: SERVICIO MTTO PREVENTIVO DINAMICAS | E41: UNIDAD | F41: 1 | G41: 23500000 | H41: =G41*(1+C$3) -> 24698500 | I41: =H41*F41 -> 24698500 | M41: =SUM(N41:Y41) -> 24698500 | N41: 0 | O41: =+N41 -> 0 | P41: =H41 -> 24698500 | Q41: 0 | R41: 0 | S41: 0 | T41: 0 | U41: 0 | V41: 0 | W41: 0 | X41: 0 | Y41: 0
A42: OPERACION DE VIAS | B42: OPERACION PESAJES | C42: OPERACION ESTACIÓN DE PESAJE MACHETA | D42: CINTA CONSPICUITI | E42: ROLLO | F42: 3 | G42: 406980 | H42: =G42*(1+C$3) -> 427735.98 | I42: =+H42*F42 -> 1283207.9 | M42: =SUM(N42:Y42) -> 1283207.9 | N42: 0 | O42: 0 | P42: 0 | Q42: 0 | R42: =H42*F42 -> 1283207.9 | S42: 0 | T42: 0 | U42: 0 | V42: 0 | W42: 0 | X42: 0 | Y42: 0
A43: OPERACION DE VIAS | B43: OPERACION PESAJES | C43: OPERACION ESTACIÓN DE PESAJE MACHETA | D43: CONOS 90 CM | E43: UNIDAD | F43: 30 | G43: 88000 | H43: =G43*(1+C$3) -> 92488 | I43: =+H43*F43 -> 2774640 | M43: =SUM(N43:Y43) -> 2774640 | N43: 0 | O43: 0 | P43: 0 | Q43: 0 | R43: 0 | S43: 0 | T43: 0 | U43: 0 | V43: =H43*F43 -> 2774640 | W43: 0 | X43: 0 | Y43: 0
A44: OPERACION DE VIAS | B44: OPERACION PESAJES | C44: OPERACION ESTACIÓN DE PESAJE MACHETA | D44: PALETAS PARE - SIGA | E44: UNIDAD | F44: 3 | G44: 41067 | H44: =G44*(1+C$3) -> 43161.417 | I44: =+H44*F44 -> 129484.25 | M44: =SUM(N44:Y44) -> 129484.25 | N44: 0 | O44: =H44*F44 -> 129484.25 | P44: 0 | Q44: 0 | R44: 0 | S44: 0 | T44: 0 | U44: 0 | V44: 0 | W44: 0 | X44: 0 | Y44: 0
A45: OPERACION DE VIAS | B45: OPERACION PESAJES | C45: OPERACION ESTACIÓN DE PESAJE MACHETA | D45: FLASHER SOLAR | E45: UNIDAD | F45: 30 | G45: 41067 | H45: =G45*(1+C$3) -> 43161.417 | I45: =+H45*F45 -> 1294842.5 | M45: =SUM(N45:Y45) -> 1294842.5 | N45: 0 | O45: 0 | P45: 0 | Q45: 0 | R45: 0 | S45: 0 | T45: 0 | U45: =H45*F45 -> 1294842.5 | V45: 0 | W45: 0 | X45: 0 | Y45: 0
A46: OPERACION DE VIAS | B46: OPERACION PESAJES | C46: OPERACION ESTACIÓN DE PESAJE MACHETA | D46: TALANQUERAS | E46: UNIDAD | F46: 3 | G46: 235620 | H46: =G46*(1+C$3) -> 247636.62 | I46: =+H46*F46 -> 742909.86 | M46: =SUM(N46:Y46) -> 742909.86 | N46: 0 | O46: =H46*F46/2 -> 371454.93 | P46: 0 | Q46: 0 | R46: 0 | S46: 0 | T46: 0 | U46: =O46 -> 371454.93 | V46: 0 | W46: 0 | X46: 0 | Y46: 0
A47: OPERACION DE VIAS | B47: OPERACION PESAJES | C47: OPERACION ESTACIÓN DE PESAJE SAN LUIS DE GACENO | M47: =SUM(M48:M57) -> 62826911 | N47: =SUM(N48:N57) -> 0 | O47: =SUM(O48:O57) -> 500939.18 | P47: =SUM(P48:P57) -> 27769036 | Q47: =SUM(Q48:Q57) -> 0 | R47: =SUM(R48:R57) -> 1283207.9 | S47: =SUM(S48:S57) -> 0 | T47: =SUM(T48:T57) -> 0 | ... Y47: =SUM(Y48:Y57) -> 0
A48: OPERACION DE VIAS | B48: OPERACION PESAJES | C48: OPERACION ESTACIÓN DE PESAJE SAN LUIS DE GACENO | D48: SERVICIO CALIBRACIÓN METROLOGICA | E48: UNIDAD | F48: 1 | G48: 14000571 | H48: =G48*(1+C$3) -> 14714600 | I48: =H48*F48 -> 14714600 | M48: =SUM(N48:Y48) -> 14714600 | N48: 0 | O48: =+N48 -> 0 | P48: 0 | Q48: 0 | R48: 0 | S48: 0 | T48: 0 | U48: 0 | V48: 0 | W48: =I48 -> 14714600 | X48: 0 | Y48: 0
A49: OPERACION DE VIAS | B49: OPERACION PESAJES | C49: OPERACION ESTACIÓN DE PESAJE SAN LUIS DE GACENO | D49: SERVICIO VERIFICACIÓN SIC | E49: UNIDAD | F49: 1 | G49: 13433102 | H49: =G49*(1+C$3) -> 14118190 | I49: =H49*F49 -> 14118190 | M49: =SUM(N49:Y49) -> 14118190 | N49: 0 | O49: 0 | P49: 0 | Q49: 0 | R49: 0 | S49: 0 | T49: 0 | U49: 0 | V49: 0 | W49: 0 | X49: =I49 -> 14118190 | Y49: 0
A50: OPERACION DE VIAS | B50: OPERACION PESAJES | C50: OPERACION ESTACIÓN DE PESAJE SAN LUIS DE GACENO | D50: SERVICIO DE ACTUALIZACIÓN BASCAM | E50: UNIDAD | F50: 0 | G50: 11894000 | H50: =G50*(1+C$3) -> 12500594 | I50: =H50*F50 -> 0 | M50: =SUM(N50:Y50) -> 0 | N50: 0 | O50: 0 | P50: 0 | Q50: 0 | R50: =I50 -> 0 | S50: 0 | T50: 0 | U50: 0 | V50: 0 | W50: 0 | X50: 0 | Y50: 0
A51: OPERACION DE VIAS | B51: OPERACION PESAJES | C51: OPERACION ESTACIÓN DE PESAJE SAN LUIS DE GACENO | D51: SERVICIO MTTO PREVENTIVO ESTATICA | E51: UNIDAD | F51: 1 | G51: 2921538 | H51: =G51*(1+C$3) -> 3070536.4 | I51: =H51*F51 -> 3070536.4 | M51: =SUM(N51:Y51) -> 3070536.4 | N51: 0 | O51: 0 | P51: =H51 -> 3070536.4 | Q51: 0 | R51: 0 | S51: 0 | T51: 0 | U51: 0 | V51: 0 | W51: 0 | X51: 0 | Y51: 0
A52: OPERACION DE VIAS | B52: OPERACION PESAJES | C52: OPERACION ESTACIÓN DE PESAJE SAN LUIS DE GACENO | D52: SERVICIO MTTO PREVENTIVO DINAMICAS | E52: UNIDAD | F52: 1 | G52: 23500000 | H52: =G52*(1+C$3) -> 24698500 | I52: =H52*F52 -> 24698500 | M52: =SUM(N52:Y52) -> 24698500 | N52: 0 | O52: =+N52 -> 0 | P52: =H52 -> 24698500 | Q52: 0 | R52: 0 | S52: 0 | T52: 0 | U52: 0 | V52: 0 | W52: 0 | X52: 0 | Y52: 0
A53: OPERACION DE VIAS | B53: OPERACION PESAJES | C53: OPERACION ESTACIÓN DE PESAJE SAN LUIS DE GACENO | D53: CINTA CONSPICUITI | E53: ROLLO | F53: 3 | G53: 406980 | H53: =G53*(1+C$3) -> 427735.98 | I53: =+H53*F53 -> 1283207.9 | M53: =SUM(N53:Y53) -> 1283207.9 | N53: 0 | O53: 0 | P53: 0 | Q53: 0 | R53: =H53*F53 -> 1283207.9 | S53: 0 | T53: 0 | U53: 0 | V53: 0 | W53: 0 | X53: 0 | Y53: 0
A54: OPERACION DE VIAS | B54: OPERACION PESAJES | C54: OPERACION ESTACIÓN DE PESAJE SAN LUIS DE GACENO | D54: CONOS 90 CM | E54: UNIDAD | F54: 30 | G54: 88000 | H54: =G54*(1+C$3) -> 92488 | I54: =+H54*F54 -> 2774640 | M54: =SUM(N54:Y54) -> 2774640 | N54: 0 | O54: 0 | P54: 0 | Q54: 0 | R54: 0 | S54: 0 | T54: 0 | U54: 0 | V54: =H54*F54 -> 2774640 | W54: 0 | X54: 0 | Y54: 0
A55: OPERACION DE VIAS | B55: OPERACION PESAJES | C55: OPERACION ESTACIÓN DE PESAJE SAN LUIS DE GACENO | D55: PALETAS PARE - SIGA | E55: UNIDAD | F55: 3 | G55: 41067 | H55: =G55*(1+C$3) -> 43161.417 | I55: =+H55*F55 -> 129484.25 | M55: =SUM(N55:Y55) -> 129484.25 | N55: 0 | O55: =H55*F55 -> 129484.25 | P55: 0 | Q55: 0 | R55: 0 | S55: 0 | T55: 0 | U55: 0 | V55: 0 | W55: 0 | X55: 0 | Y55: 0
A56: OPERACION DE VIAS | B56: OPERACION PESAJES | C56: OPERACION ESTACIÓN DE PESAJE SAN LUIS DE GACENO | D56: FLASHER SOLAR | E56: UNIDAD | F56: 30 | G56: 41067 | H56: =G56*(1+C$3) -> 43161.417 | I56: =+H56*F56 -> 1294842.5 | M56: =SUM(N56:Y56) -> 1294842.5 | N56: 0 | O56: 0 | P56: 0 | Q56: 0 | R56: 0 | S56: 0 | T56: 0 | U56: =H56*F56 -> 1294842.5 | V56: 0 | W56: 0 | X56: 0 | Y56: 0
A57: OPERACION DE VIAS | B57: OPERACION PESAJES | C57: OPERACION ESTACIÓN DE PESAJE SAN LUIS DE GACENO | D57: TALANQUERAS | E57: UNIDAD | F57: 3 | G57: 235620 | H57: =G57*(1+C$3) -> 247636.62 | I57: =+H57*F57 -> 742909.86 | M57: =SUM(N57:Y57) -> 742909.86 | N57: 0 | O57: =H57*F57/2 -> 371454.93 | P57: 0 | Q57: 0 | R57: 0 | S57: 0 | T57: 0 | U57: =O57 -> 371454.93 | V57: 0 | W57: 0 | X57: 0 | Y57: 0
A58: OPERACION DE VIAS | B58: OPERACION CCO, BASES DE OPERACIONES Y ÁREAS DE SERVICIO | C58: OPERACION CCO, BASES DE OPERACIONES Y ÁREAS DE SERVICIO | M58: =SUM(N58:Y58) -> 1.98369e+09 | N58: =SUM(N59:N81) -> 1.4784993e+08 | O58: =SUM(O59:O81) -> 1.4784993e+08 | P58: =SUM(P59:P81) -> 2.2070565e+08 | Q58: =SUM(Q59:Q81) -> 1.4890093e+08 | R58: =SUM(R59:R81) -> 1.8656511e+08 | S58: =SUM(S59:S81) -> 1.4784993e+08 | T58: =SUM(T59:T81) -> 1.5391339e+08 | U58: =SUM(U59:U81) -> 1.4784993e+08 | ... Y58: =SUM(Y59:Y81) -> 1.4784993e+08
A59: OPERACION DE VIAS | B59: OPERACION CCO, BASES DE OPERACIONES Y ÁREAS DE SERVICIO | C59: OPERACION CCO, BASES DE OPERACIONES Y ÁREAS DE SERVICIO | D59: SERVICIO AMBULANCIA TAM | E59: MES | F59: 12 | G59: 116866800 | H59: =(G59*0.7*(1+C$4))+(G59*0.3*(1+C$3)) -> 1.3747042e+08 | I59: =+H59*F59 -> 1.649645e+09 | M59: =SUM(N59:Y59) -> 1.649645e+09 | N59: =H59 -> 1.3747042e+08 | O59: =+N59 -> 1.3747042e+08 | P59: =+O59 -> 1.3747042e+08 | Q59: =+P59 -> 1.3747042e+08 | R59: =+Q59 -> 1.3747042e+08 | S59: =+R59 -> 1.3747042e+08 | T59: =+S59 -> 1.3747042e+08 | U59: =+T59 -> 1.3747042e+08 | V59: =+U59 -> 1.3747042e+08 | ... Y59: =+X59 -> 1.3747042e+08
A60: OPERACION DE VIAS | B60: OPERACION CCO, BASES DE OPERACIONES Y ÁREAS DE SERVICIO | C60: OPERACION CCO, BASES DE OPERACIONES Y ÁREAS DE SERVICIO | D60: SERVICIO ALQUILER EQUIPOS RESPIRACIÓN AUTONÓMA | E60: MES | F60: 12 | G60: 2025000 | H60: =G60*(1+C$3) -> 2128275 | I60: =+H60*F60 -> 25539300 | M60: =SUM(N60:Y60) -> 25539300 | N60: =H60 -> 2128275 | O60: =N60 -> 2128275 | P60: =O60 -> 2128275 | Q60: =P60 -> 2128275 | R60: =Q60 -> 2128275 | S60: =R60 -> 2128275 | T60: =S60 -> 2128275 | U60: =T60 -> 2128275 | V60: =U60 -> 2128275 | ... Y60: =X60 -> 2128275
A61: OPERACION DE VIAS | B61: OPERACION CCO, BASES DE OPERACIONES Y ÁREAS DE SERVICIO | C61: OPERACION CCO, BASES DE OPERACIONES Y ÁREAS DE SERVICIO | D61: SERVICIO MTTO SICC | E61: MES | F61: 12 | G61: 4936391 | H61: =G61*(1+C$3) -> 5188146.9 | I61: =+H61*F61 -> 62257763 | M61: =SUM(N61:Y61) -> 62257763 | N61: =H61 -> 5188146.9 | O61: =N61 -> 5188146.9 | P61: =O61 -> 5188146.9 | Q61: =P61 -> 5188146.9 | R61: =Q61 -> 5188146.9 | S61: =R61 -> 5188146.9 | T61: =S61 -> 5188146.9 | U61: =T61 -> 5188146.9 | V61: =U61 -> 5188146.9 | ... Y61: =X61 -> 5188146.9
A62: OPERACION DE VIAS | B62: OPERACION CCO, BASES DE OPERACIONES Y ÁREAS DE SERVICIO | C62: OPERACION CCO, BASES DE OPERACIONES Y ÁREAS DE SERVICIO | D62: SERVICIO DISPONIBILIDAD SICC | E62: MES | F62: 12 | G62: =1011500 -> 1011500 | H62: =G62*(1+C$3) -> 1063086.5 | I62: =+H62*F62 -> 12757038 | M62: =SUM(N62:Y62) -> 12757038 | N62: =H62 -> 1063086.5 | O62: =N62 -> 1063086.5 | P62: =O62 -> 1063086.5 | Q62: =P62 -> 1063086.5 | R62: =Q62 -> 1063086.5 | S62: =R62 -> 1063086.5 | T62: =S62 -> 1063086.5 | U62: =T62 -> 1063086.5 | V62: =U62 -> 1063086.5 | ... Y62: =X62 -> 1063086.5
A63: OPERACION DE VIAS | B63: OPERACION CCO, BASES DE OPERACIONES Y ÁREAS DE SERVICIO | C63: OPERACION CCO, BASES DE OPERACIONES Y ÁREAS DE SERVICIO | D63: INSUMOS ENFERMERIAS | E63: GLOBAL | F63: 1 | G63: =1040000/1.04 -> 1000000 | H63: =G63*(1+C$3) -> 1051000 | I63: =+H63*F63 -> 1051000 | M63: =SUM(N63:Y63) -> 1051000 | N63: 0 | O63: 0 | P63: 0 | Q63: =I63 -> 1051000 | R63: 0 | S63: 0 | T63: 0 | U63: 0 | V63: 0 | W63: 0 | X63: 0 | Y63: 0
A64: OPERACION DE VIAS | B64: OPERACION CCO, BASES DE OPERACIONES Y ÁREAS DE SERVICIO | C64: OPERACION CCO, BASES DE OPERACIONES Y ÁREAS DE SERVICIO | D64: INSUMOS TALLERES MECANICOS | E64: GLOBAL | F64: 1 | G64: =6000000/1.04 -> 5769230.8 | H64: =G64*(1+C$3) -> 6063461.5 | I64: =+H64*F64 -> 6063461.5 | M64: =SUM(N64:Y64) -> 6063461.5 | N64: 0 | O64: 0 | P64: 0 | Q64: 0 | R64: 0 | S64: 0 | T64: =I64 -> 6063461.5 | U64: 0 | V64: 0 | W64: 0 | X64: 0 | Y64: 0
A65: OPERACION DE VIAS | B65: OPERACION CCO, BASES DE OPERACIONES Y ÁREAS DE SERVICIO | C65: OPERACION CCO, BASES DE OPERACIONES Y ÁREAS DE SERVICIO | D65: SERIVICO ALQUILER GRUA PLATAFORMA | E65: DIA | F65: 14 | G65: 1261400 | H65: =G65*(1+C$3) -> 1325731.4 | I65: =+H65*F65 -> 18560240 | M65: =SUM(N65:Y65) -> 18560240 | N65: 0 | O65: 0 | P65: =H65*7 -> 9280119.8 | Q65: 0 | R65: 0 | S65: 0 | T65: 0 | U65: 0 | V65: =H65*7 -> 9280119.8 | W65: 0 | X65: 0 | Y65: 0
A66: OPERACION DE VIAS | B66: OPERACION CCO, BASES DE OPERACIONES Y ÁREAS DE SERVICIO | C66: OPERACION CCO, BASES DE OPERACIONES Y ÁREAS DE SERVICIO | D66: SERVICIO ALQUILER GRUA GANCHO | E66: DIA | F66: 30 | G66: 2380000 | H66: =G66*(1+C$3) -> 2501380 | I66: =+H66*F66 -> 75041400 | M66: =SUM(N66:Y66) -> 75041400 | N66: 0 | O66: 0 | P66: =H66*15 -> 37520700 | Q66: 0 | R66: 0 | S66: 0 | T66: 0 | U66: 0 | V66: =H66*15 -> 37520700 | W66: 0 | X66: 0 | Y66: 0
A67: OPERACION DE VIAS | B67: OPERACION CCO, BASES DE OPERACIONES Y ÁREAS DE SERVICIO | C67: OPERACION CCO, BASES DE OPERACIONES Y ÁREAS DE SERVICIO | D67: VALLA PROYECTO | E67: ANUAL | F67: 1 | G67: 31800000 | H67: =G67*(1+C$3) -> 33421800 | I67: =+H67*F67 -> 33421800 | M67: =SUM(N67:Y67) -> 0 | N67: 0 | O67: 0 | P67: 0 | Q67: 0 | R67: 0 | S67: 0 | T67: 0 | U67: 0 | V67: 0 | W67: 0 | X67: 0 | Y67: 0
A68: OPERACION DE VIAS | B68: OPERACION CCO, BASES DE OPERACIONES Y ÁREAS DE SERVICIO | C68: OPERACION CCO, BASES DE OPERACIONES Y ÁREAS DE SERVICIO | D68: CAMPANAS PLASTICAS REFLECTIVOS | E68: UNIDAD | F68: 70 | G68: 210792 | H68: =G68*(1+C$3) -> 221542.39 | I68: =+H68*F68 -> 15507967 | M68: =SUM(N68:Y68) -> 15507967 | N68: 0 | O68: 0 | P68: 0 | Q68: 0 | R68: =H68*35 -> 7753983.7 | S68: 0 | T68: 0 | U68: 0 | V68: 0 | W68: =R68 -> 7753983.7 | X68: 0 | Y68: 0
A69: OPERACION DE VIAS | B69: OPERACION CCO, BASES DE OPERACIONES Y ÁREAS DE SERVICIO | C69: OPERACION CCO, BASES DE OPERACIONES Y ÁREAS DE SERVICIO | D69: BARRERA PLASTICAS REFLECTIVO | E69: UNIDAD | F69: 70 | G69: 330896 | H69: =G69*(1+C$3) -> 347771.7 | I69: =+H69*F69 -> 24344019 | M69: =SUM(N69:Y69) -> 24344019 | N69: 0 | O69: 0 | P69: 0 | Q69: 0 | R69: =H69*35 -> 12172009 | S69: 0 | T69: 0 | U69: 0 | V69: 0 | W69: =R69 -> 12172009 | X69: 0 | Y69: 0
A70: OPERACION DE VIAS | B70: OPERACION CCO, BASES DE OPERACIONES Y ÁREAS DE SERVICIO | C70: OPERACION CCO, BASES DE OPERACIONES Y ÁREAS DE SERVICIO | D70: DELINEADOR TUBULAR REFLECTIVO | E70: UNIDAD | F70: 50 | G70: 38484 | H70: =G70*(1+C$3) -> 40446.684 | I70: =+H70*F70 -> 2022334.2 | M70: =SUM(N70:Y70) -> 2022334.2 | N70: 0 | O70: 0 | P70: 0 | Q70: 0 | R70: =H70*25 -> 1011167.1 | S70: 0 | T70: 0 | U70: 0 | V70: 0 | W70: =R70 -> 1011167.1 | X70: 0 | Y70: 0
A71: OPERACION DE VIAS | B71: OPERACION CCO, BASES DE OPERACIONES Y ÁREAS DE SERVICIO | C71: OPERACION CCO, BASES DE OPERACIONES Y ÁREAS DE SERVICIO | D71: CINTA SEÑALIZACIÓN PELIGRO | E71: ROLLO | F71: 50 | G71: 18550 | H71: =G71*(1+C$3) -> 19496.05 | I71: =+H71*F71 -> 974802.5 | M71: =SUM(N71:Y71) -> 974802.5 | N71: 0 | O71: 0 | P71: 0 | Q71: 0 | R71: =H71*25 -> 487401.25 | S71: 0 | T71: 0 | U71: 0 | V71: 0 | W71: =R71 -> 487401.25 | X71: 0 | Y71: 0
A72: OPERACION DE VIAS | B72: OPERACION CCO, BASES DE OPERACIONES Y ÁREAS DE SERVICIO | C72: OPERACION CCO, BASES DE OPERACIONES Y ÁREAS DE SERVICIO | D72: PALETA PARE Y SIGA | E72: UNIDAD | F72: 16 | G72: 107590 | H72: =G72*(1+C$3) -> 113077.09 | I72: =+H72*F72 -> 1809233.4 | M72: =SUM(N72:Y72) -> 1809233.4 | N72: 0 | O72: 0 | P72: 0 | Q72: 0 | R72: =H72*8 -> 904616.72 | S72: 0 | T72: 0 | U72: 0 | V72: 0 | W72: =R72 -> 904616.72 | X72: 0 | Y72: 0
A73: OPERACION DE VIAS | B73: OPERACION CCO, BASES DE OPERACIONES Y ÁREAS DE SERVICIO | C73: OPERACION CCO, BASES DE OPERACIONES Y ÁREAS DE SERVICIO | D73: BASTON LUMINOSO | E73: UNIDAD | F73: 16 | G73: 119000 | H73: =G73*(1+C$3) -> 125069 | I73: =+H73*F73 -> 2001104 | M73: =SUM(N73:Y73) -> 2001104 | N73: 0 | O73: 0 | P73: 0 | Q73: 0 | R73: =H73*8 -> 1000552 | S73: 0 | T73: 0 | U73: 0 | V73: 0 | W73: =R73 -> 1000552 | X73: 0 | Y73: 0
A74: OPERACION DE VIAS | B74: OPERACION CCO, BASES DE OPERACIONES Y ÁREAS DE SERVICIO | C74: OPERACION CCO, BASES DE OPERACIONES Y ÁREAS DE SERVICIO | D74: CONO 90 CM | E74: UNIDAD | F74: 70 | G74: 107100 | H74: =G74*(1+C$3) -> 112562.1 | I74: =+H74*F74 -> 7879347 | M74: =SUM(N74:Y74) -> 7879347 | N74: 0 | O74: 0 | P74: 0 | Q74: 0 | R74: =H74*35 -> 3939673.5 | S74: 0 | T74: 0 | U74: 0 | V74: 0 | W74: =R74 -> 3939673.5 | X74: 0 | Y74: 0
A75: OPERACION DE VIAS | B75: OPERACION CCO, BASES DE OPERACIONES Y ÁREAS DE SERVICIO | C75: OPERACION CCO, BASES DE OPERACIONES Y ÁREAS DE SERVICIO | D75: FLASCHER LUMINOSO | E75: UNIDAD | F75: 16 | G75: 95200 | H75: =G75*(1+C$3) -> 100055.2 | I75: =+H75*F75 -> 1600883.2 | M75: =SUM(N75:Y75) -> 1600883.2 | N75: 0 | O75: 0 | P75: 0 | Q75: 0 | R75: =H75*8 -> 800441.6 | S75: 0 | T75: 0 | U75: 0 | V75: 0 | W75: =R75 -> 800441.6 | X75: 0 | Y75: 0
A76: OPERACION DE VIAS | B76: OPERACION CCO, BASES DE OPERACIONES Y ÁREAS DE SERVICIO | C76: OPERACION CCO, BASES DE OPERACIONES Y ÁREAS DE SERVICIO | D76: SEÑALES PREVENTIVAS EVENTOS ESPECIALES CON TRIPODE | E76: UNIDAD | F76: 10 | G76: =337360+149932 -> 487292 | H76: =G76*(1+C$3) -> 512143.89 | I76: =+H76*F76 -> 5121438.9 | M76: =SUM(N76:Y76) -> 5121438.9 | N76: 0 | O76: 0 | P76: 0 | Q76: 0 | R76: =H76*5 -> 2560719.5 | S76: 0 | T76: 0 | U76: 0 | V76: 0 | W76: =R76 -> 2560719.5 | X76: 0 | Y76: 0
A77: OPERACION DE VIAS | B77: OPERACION CCO, BASES DE OPERACIONES Y ÁREAS DE SERVICIO | C77: OPERACION CCO, BASES DE OPERACIONES Y ÁREAS DE SERVICIO | D77: HERRAMIENTAS MANUALES (PALAS, ESCOBONES, MACHETAS) | E77: GLOBAL | F77: 1 | G77: =2143066/1.04 -> 2060640.4 | H77: =G77*(1+C$3) -> 2165733 | I77: =+H77*F77 -> 2165733 | M77: =SUM(N77:Y77) -> 2165733 | N77: 0 | O77: 0 | P77: =H77 -> 2165733 | Q77: 0 | R77: 0 | S77: 0 | T77: 0 | U77: 0 | V77: 0 | W77: 0 | X77: 0 | Y77: 0
A78: OPERACION DE VIAS | B78: OPERACION CCO, BASES DE OPERACIONES Y ÁREAS DE SERVICIO | C78: OPERACION CCO, BASES DE OPERACIONES Y ÁREAS DE SERVICIO | D78: HERRAMIENTAS EQUIPOS CARRO TALLER | E78: GLOBAL | F78: 1 | G78: =8000000/1.04 -> 7692307.7 | H78: =G78*(1+C$3) -> 8084615.4 | I78: =+H78*F78 -> 8084615.4 | M78: =SUM(N78:Y78) -> 8084615.4 | N78: 0 | O78: 0 | P78: 0 | Q78: 0 | R78: =H78 -> 8084615.4 | S78: 0 | T78: 0 | U78: 0 | V78: 0 | W78: 0 | X78: 0 | Y78: 0
A79: OPERACION DE VIAS | B79: OPERACION CCO, BASES DE OPERACIONES Y ÁREAS DE SERVICIO | C79: OPERACION CCO, BASES DE OPERACIONES Y ÁREAS DE SERVICIO | D79: HERRAMIENTAS, ELEMENTOS DE AMARRE PARA GRUA PLATAFORMA | E79: GLOBAL | F79: 1 | G79: =10404940/1.04 -> 10004750 | H79: =G79*(1+C$3) -> 10514992 | I79: =+H79*F79 -> 10514992 | M79: =SUM(N79:Y79) -> 10514992 | N79: 0 | O79: 0 | P79: =H79 -> 10514992 | Q79: 0 | R79: 0 | S79: 0 | T79: 0 | U79: 0 | V79: 0 | W79: 0 | X79: 0 | Y79: 0
A80: OPERACION DE VIAS | B80: OPERACION CCO, BASES DE OPERACIONES Y ÁREAS DE SERVICIO | C80: OPERACION CCO, BASES DE OPERACIONES Y ÁREAS DE SERVICIO | D80: HERRAMIENTAS Y ELEMENTOS DE AMARRE PARA GRUA GANCHO | E80: GLOBAL | F80: 1 | G80: =26468406/1.04 -> 25450390 | H80: =G80*(1+C$3) -> 26748360 | I80: =+H80*F80 -> 26748360 | M80: =SUM(N80:Y80) -> 26748360 | N80: 0 | O80: 0 | P80: =H80/2 -> 13374180 | Q80: 0 | R80: 0 | S80: 0 | T80: 0 | U80: 0 | V80: =P80 -> 13374180 | W80: 0 | X80: 0 | Y80: 0
A81: OPERACION DE VIAS | B81: OPERACION CCO, BASES DE OPERACIONES Y ÁREAS DE SERVICIO | C81: OPERACION CCO, BASES DE OPERACIONES Y ÁREAS DE SERVICIO | D81: CAJA MENOR | E81: MES | F81: 12 | G81: 2000000 | H81: =G81 -> 2000000 | I81: =+H81*F81 -> 24000000 | M81: =SUM(N81:Y81) -> 24000000 | N81: =H81 -> 2000000 | O81: =N81 -> 2000000 | P81: =O81 -> 2000000 | Q81: =P81 -> 2000000 | R81: =Q81 -> 2000000 | S81: =R81 -> 2000000 | T81: =S81 -> 2000000 | U81: =T81 -> 2000000 | V81: =U81 -> 2000000 | ... Y81: =X81 -> 2000000
A82: OPERACION DE VIAS | B82: MANTENIMIENTO DE EQUIPOS DE OPERACIONES | C82: MANTENIMIENTO CAMIONETAS TOYOTA | M82: =SUM(N82:Y82) -> 4.8482678e+08 | N82: =SUM(N86:N101) -> 38560014 | O82: =SUM(O86:O101) -> 42705941 | P82: =SUM(P86:P101) -> 38560014 | Q82: =SUM(Q86:Q101) -> 38560014 | R82: =SUM(R86:R101) -> 52374778 | S82: =SUM(S86:S101) -> 38560014 | T82: =SUM(T86:T101) -> 38560014 | U82: =SUM(U86:U101) -> 38560014 | ... Y82: =SUM(Y86:Y101) -> 39941989
A83: OPERACION DE VIAS | B83: MANTENIMIENTO DE EQUIPOS DE OPERACIONES | C83: MANTENIMIENTO CAMIONETAS TOYOTA | D83: SEGURO TODO RIESGO CAMIONETAS TOYOTA 2017 | G83: 0 | H83: =G83*(1+C$3) -> 0 | I83: =+H83*F83 -> 0 | M83: =SUM(N83:Y83) -> 0 | N83: 0 | O83: =I83 -> 0 | P83: 0 | Q83: 0 | R83: 0 | S83: 0 | T83: 0 | U83: 0 | V83: 0 | W83: 0 | X83: 0 | Y83: 0
A84: OPERACION DE VIAS | B84: MANTENIMIENTO DE EQUIPOS DE OPERACIONES | C84: MANTENIMIENTO CAMIONETAS TOYOTA | D84: SEGURO TODO RIESGO CAMIONETAS TOYOTA 2018 | G84: 0 | H84: =G84*(1+C$3) -> 0 | I84: =+H84*F84 -> 0 | M84: =SUM(N84:Y84) -> 0 | N84: 0 | O84: =I84 -> 0 | P84: 0 | Q84: 0 | S84: 0 | T84: 0 | U84: 0 | V84: 0 | W84: 0 | X84: 0 | Y84: 0
A85: OPERACION DE VIAS | B85: MANTENIMIENTO DE EQUIPOS DE OPERACIONES | C85: MANTENIMIENTO CAMIONETAS TOYOTA | D85: SEGURO TODO RIESGO CAMIONETAS TOYOTA 2019 | G85: 0 | H85: =G85*(1+C$3) -> 0 | I85: =+H85*F85 -> 0 | M85: =SUM(N85:Y85) -> 0 | N85: 0 | O85: =I85 -> 0 | P85: 0 | Q85: 0 | S85: 0 | T85: 0 | U85: 0 | V85: 0 | W85: 0 | X85: 0 | Y85: 0
A86: OPERACION DE VIAS | B86: MANTENIMIENTO DE EQUIPOS DE OPERACIONES | C86: MANTENIMIENTO CAMIONETAS TOYOTA | D86: SERVICIO IMPUESTO AÑO GRAVABLE 2026 CAMIONETAS TOYOTA 2017 | E86: UNIDAD | F86: 1 | G86: 2316900 | H86: =G86*(1+C$3) -> 2435061.9 | I86: =+H86*F86 -> 2435061.9 | M86: =SUM(N86:Y86) -> 2435061.9 | N86: 0 | O86: 0 | P86: 0 | Q86: 0 | R86: =I86*F86 -> 2435061.9 | S86: 0 | T86: 0 | U86: 0 | V86: 0 | W86: 0 | X86: 0 | Y86: 0
A87: OPERACION DE VIAS | B87: MANTENIMIENTO DE EQUIPOS DE OPERACIONES | C87: MANTENIMIENTO CAMIONETAS TOYOTA | D87: SERVICIO IMPUESTO AÑO GRAVABLE 2026 CAMIONETAS TOYOTA 2018 | E87: UNIDAD | F87: 1 | G87: 2499900 | H87: =G87*(1+C$3) -> 2627394.9 | I87: =+H87*F87 -> 2627394.9 | M87: =SUM(N87:Y87) -> 2627394.9 | N87: 0 | O87: 0 | P87: 0 | Q87: 0 | R87: =I87*F87 -> 2627394.9 | S87: 0 | T87: 0 | U87: 0 | V87: 0 | W87: 0 | X87: 0 | Y87: 0
A88: OPERACION DE VIAS | B88: MANTENIMIENTO DE EQUIPOS DE OPERACIONES | C88: MANTENIMIENTO CAMIONETAS TOYOTA | D88: SERVICIO IMPUESTO AÑO GRAVABLE 2026 CAMIONETAS TOYOTA 2019 | E88: UNIDAD | F88: 4 | G88: 2081900 | H88: =G88*(1+C$3) -> 2188076.9 | I88: =+H88*F88 -> 8752307.6 | M88: =SUM(N88:Y88) -> 8752307.6 | N88: 0 | O88: 0 | P88: 0 | Q88: 0 | R88: =H88*F88 -> 8752307.6 | S88: 0 | T88: 0 | U88: 0 | V88: 0 | W88: 0 | X88: 0 | Y88: 0
A89: OPERACION DE VIAS | B89: MANTENIMIENTO DE EQUIPOS DE OPERACIONES | C89: MANTENIMIENTO CAMIONETAS TOYOTA | D89: SEGURO SOAT | E89: UNIDAD | F89: 6 | G89: 980512 | H89: =G89*(1+C$3) -> 1030518.1 | I89: =+H89*F89 -> 6183108.7 | M89: =SUM(N89:Y89) -> 6183108.7 | N89: 0 | O89: =H89*3 -> 3091554.3 | P89: 0 | Q89: 0 | R89: 0 | S89: 0 | T89: 0 | U89: 0 | V89: =H89 -> 1030518.1 | W89: 0 | X89: =H89 -> 1030518.1 | Y89: =H89 -> 1030518.1
A90: OPERACION DE VIAS | B90: MANTENIMIENTO DE EQUIPOS DE OPERACIONES | C90: MANTENIMIENTO CAMIONETAS TOYOTA | D90: SERVICIO REVISIÓN TECNICOMECÁNICA | E90: UNIDAD | F90: 6 | G90: 334403 | H90: =G90*(1+C$3) -> 351457.55 | I90: =+H90*F90 -> 2108745.3 | M90: =SUM(N90:Y90) -> 2108745.3 | N90: 0 | O90: =H90*3 -> 1054372.7 | P90: 0 | Q90: 0 | R90: 0 | S90: 0 | T90: 0 | U90: 0 | V90: =H90 -> 351457.55 | W90: 0 | X90: =H90 -> 351457.55 | Y90: =H90 -> 351457.55
A91: OPERACION DE VIAS | B91: MANTENIMIENTO DE EQUIPOS DE OPERACIONES | C91: MANTENIMIENTO CAMIONETAS TOYOTA | D91: SERVICIO CONTROL SATELITAL | E91: UNIDAD | F91: 6 | G91: =43779*12 -> 525348 | H91: =G91*(1+C$3) -> 552140.75 | I91: =+H91*F91 -> 3312844.5 | M91: =SUM(N91:Y91) -> 39754134 | N91: =H91*F91 -> 3312844.5 | O91: =N91 -> 3312844.5 | P91: =O91 -> 3312844.5 | Q91: =P91 -> 3312844.5 | R91: =Q91 -> 3312844.5 | S91: =R91 -> 3312844.5 | T91: =S91 -> 3312844.5 | U91: =T91 -> 3312844.5 | V91: =U91 -> 3312844.5 | ... Y91: =X91 -> 3312844.5
A92: OPERACION DE VIAS | B92: MANTENIMIENTO DE EQUIPOS DE OPERACIONES | C92: MANTENIMIENTO CAMIONETAS TOYOTA | D92: COMBUSTIBLE ACPM | E92: GN | F92: =M92/H92 -> 6609.9854 | G92: 12689 | H92: =G92*(1+C$3) -> 13336.139 | I92: =+H92*F92 -> 88151684 | M92: =SUM(N92:Y92) -> 88151684 | N92: 7345973.7 | O92: 7345973.7 | P92: 7345973.7 | Q92: 7345973.7 | R92: 7345973.7 | S92: 7345973.7 | T92: 7345973.7 | U92: 7345973.7 | V92: 7345973.7 | W92: 7345973.7 | X92: 7345973.7 | Y92: 7345973.7
A93: OPERACION DE VIAS | B93: MANTENIMIENTO DE EQUIPOS DE OPERACIONES | C93: MANTENIMIENTO CAMIONETAS TOYOTA | D93: FILTRO DE AIRE CAMIONETA TOYOTA 2017-2019-2024 | E93: UNIDAD | F93: =12*6 -> 72 | G93: 79900 | H93: =G93*(1+C$3) -> 83974.9 | I93: =+H93*F93 -> 6046192.8 | M93: =SUM(N93:Y93) -> 72554314 | N93: =H93*F93 -> 6046192.8 | O93: =N93 -> 6046192.8 | P93: =O93 -> 6046192.8 | Q93: =P93 -> 6046192.8 | R93: =Q93 -> 6046192.8 | S93: =R93 -> 6046192.8 | T93: =S93 -> 6046192.8 | U93: =T93 -> 6046192.8 | V93: =U93 -> 6046192.8 | ... Y93: =X93 -> 6046192.8
A94: OPERACION DE VIAS | B94: MANTENIMIENTO DE EQUIPOS DE OPERACIONES | C94: MANTENIMIENTO CAMIONETAS TOYOTA | D94: FILTRO ACEITE CAMIONETA TOYOTA 2017-2019-2024 | E94: UNIDAD | F94: =12*6 -> 72 | G94: 40000 | H94: =G94*(1+C$3) -> 42040 | I94: =+H94*F94 -> 3026880 | M94: =SUM(N94:Y94) -> 36322560 | N94: =H94*F94 -> 3026880 | O94: =N94 -> 3026880 | P94: =O94 -> 3026880 | Q94: =P94 -> 3026880 | R94: =Q94 -> 3026880 | S94: =R94 -> 3026880 | T94: =S94 -> 3026880 | U94: =T94 -> 3026880 | V94: =U94 -> 3026880 | ... Y94: =X94 -> 3026880
A95: OPERACION DE VIAS | B95: MANTENIMIENTO DE EQUIPOS DE OPERACIONES | C95: MANTENIMIENTO CAMIONETAS TOYOTA | D95: FILTRO ACPM CAMIONETA TOYOTA 2017-2019-2024 | E95: UNIDAD | F95: =12*6 -> 72 | G95: 31185 | H95: =G95*(1+C$3) -> 32775.435 | I95: =+H95*F95 -> 2359831.3 | M95: =SUM(N95:Y95) -> 28317976 | N95: =H95*F95 -> 2359831.3 | O95: =N95 -> 2359831.3 | P95: =O95 -> 2359831.3 | Q95: =P95 -> 2359831.3 | R95: =Q95 -> 2359831.3 | S95: =R95 -> 2359831.3 | T95: =S95 -> 2359831.3 | U95: =T95 -> 2359831.3 | V95: =U95 -> 2359831.3 | ... Y95: =X95 -> 2359831.3
A96: OPERACION DE VIAS | B96: MANTENIMIENTO DE EQUIPOS DE OPERACIONES | C96: MANTENIMIENTO CAMIONETAS TOYOTA | D96: FILTRO AIRE ACONDICIONADO CAMIONETA TOYOTA 2017-2019-2024 | E96: UNIDAD | F96: =12*6 -> 72 | G96: 44900 | H96: =G96*(1+C$3) -> 47189.9 | I96: =+H96*F96 -> 3397672.8 | M96: =SUM(N96:Y96) -> 40772074 | N96: =H96*F96 -> 3397672.8 | O96: =N96 -> 3397672.8 | P96: =O96 -> 3397672.8 | Q96: =P96 -> 3397672.8 | R96: =Q96 -> 3397672.8 | S96: =R96 -> 3397672.8 | T96: =S96 -> 3397672.8 | U96: =T96 -> 3397672.8 | V96: =U96 -> 3397672.8 | ... Y96: =X96 -> 3397672.8
A97: OPERACION DE VIAS | B97: MANTENIMIENTO DE EQUIPOS DE OPERACIONES | C97: MANTENIMIENTO CAMIONETAS TOYOTA | D97: ARANDELA TAPON CARTER CAMIONETA TOYOTA 2017-2019-2024 | E97: UNIDAD | F97: =12*6 -> 72 | G97: 5000 | H97: =G97*(1+C$3) -> 5255 | I97: =+H97*F97 -> 378360 | M97: =SUM(N97:Y97) -> 4540320 | N97: =H97*F97 -> 378360 | O97: =N97 -> 378360 | P97: =O97 -> 378360 | Q97: =P97 -> 378360 | R97: =Q97 -> 378360 | S97: =R97 -> 378360 | T97: =S97 -> 378360 | U97: =T97 -> 378360 | V97: =U97 -> 378360 | ... Y97: =X97 -> 378360
A98: OPERACION DE VIAS | B98: MANTENIMIENTO DE EQUIPOS DE OPERACIONES | C98: MANTENIMIENTO CAMIONETAS TOYOTA | D98: ACEITE 15W40 CAMIONETA TOYOTA 2017-2019-2024 | E98: GN | F98: =24*6 -> 144 | G98: 72363.64 | H98: =G98*(1+C$3) -> 76054.186 | I98: =+H98*F98 -> 10951803 | M98: =SUM(N98:Y98) -> 1.3142163e+08 | N98: =H98*F98 -> 10951803 | O98: =N98 -> 10951803 | P98: =O98 -> 10951803 | Q98: =P98 -> 10951803 | R98: =Q98 -> 10951803 | S98: =R98 -> 10951803 | T98: =S98 -> 10951803 | U98: =T98 -> 10951803 | V98: =U98 -> 10951803 | ... Y98: =X98 -> 10951803
A99: OPERACION DE VIAS | B99: MANTENIMIENTO DE EQUIPOS DE OPERACIONES | C99: MANTENIMIENTO CAMIONETAS TOYOTA | D99: REFRIGERANTE ROJO | E99: UNIDAD | F99: =2*6 -> 12 | G99: 37000 | H99: =G99*(1+C$3) -> 38887 | I99: =+H99*F99 -> 466644 | M99: =SUM(N99:Y99) -> 5599728 | N99: =H99*F99 -> 466644 | O99: =N99 -> 466644 | P99: =O99 -> 466644 | Q99: =P99 -> 466644 | R99: =Q99 -> 466644 | S99: =R99 -> 466644 | T99: =S99 -> 466644 | U99: =T99 -> 466644 | V99: =U99 -> 466644 | ... Y99: =X99 -> 466644
A100: OPERACION DE VIAS | B100: MANTENIMIENTO DE EQUIPOS DE OPERACIONES | C100: MANTENIMIENTO CAMIONETAS TOYOTA | D100: LIQUIDO DE FRENOS DOT 4 SL LITRO | E100: LITRO | F100: =2*6 -> 12 | G100: 55000 | H100: =G100*(1+C$3) -> 57805 | I100: =+H100*F100 -> 693660 | M100: =SUM(N100:Y100) -> 8323920 | N100: =H100*F100 -> 693660 | O100: =N100 -> 693660 | P100: =O100 -> 693660 | Q100: =P100 -> 693660 | R100: =Q100 -> 693660 | S100: =R100 -> 693660 | T100: =S100 -> 693660 | U100: =T100 -> 693660 | V100: =U100 -> 693660 | ... Y100: =X100 -> 693660
A101: OPERACION DE VIAS | B101: MANTENIMIENTO DE EQUIPOS DE OPERACIONES | C101: MANTENIMIENTO CAMIONETAS TOYOTA | D101: ACEITE DIFERENCIAL Y TRANSMISIÓN 85W90 | E101: LITRO | F101: =8*6 -> 48 | G101: 138000 | H101: =G101*(1+C$3) -> 145038 | I101: =+H101*F101 -> 6961824 | M101: =SUM(N101:Y101) -> 6961824 | N101: =H101*F101/12 -> 580152 | O101: =N101 -> 580152 | P101: =O101 -> 580152 | Q101: =P101 -> 580152 | R101: =Q101 -> 580152 | S101: =R101 -> 580152 | T101: =S101 -> 580152 | U101: =T101 -> 580152 | V101: =U101 -> 580152 | ... Y101: =X101 -> 580152
A102: OPERACION DE VIAS | B102: MANTENIMIENTO DE EQUIPOS DE OPERACIONES | C102: MANTENIMIENTO CAMIONETAS TOYOTA | D102: SERVICIO CAMBIO CADENA DE REPARTICION | E102: UNIDAD | F102: 2 | G102: 1800000 | H102: =G102*(1+C$3) -> 1891800 | I102: =H102*F102 -> 3783600 | M102: =SUM(N102:Y102) -> 3783600 | N102: 0 | O102: 0 | P102: 0 | Q102: 0 | R102: 0 | S102: 0 | T102: 3783600 | U102: 0 | V102: 0 | W102: 0 | X102: 0 | Y102: 0
...

Sheet Polca
B2: Variable
B3: IPC (dic/dic) | C3: 4,0%
B4: Salario mínimo | C4: 0.08
B5: TRM promedio (COP/USD) | C5: $4.250
A7: Capítulo | B7: ítem | C7: Insumo | D7: Descripción | E7: Unidad | F7: Cantidad 2026 | G7: Precio Base 2025 | H7: Precio Base 2026 | I7: Valor Total | J7: Supuestos | K7: Observaciones | L7: Soporte | M7: Total Presupuesto 2026 | N7: Enero | O7: febrero | P7: marzo | Q7: abril | R7: mayo | S7: junio | T7: julio | U7: agosto | V7: septiembre | W7: octubre | X7: noviembre | Y7: diciembre
A8: POLICIA DE CARRETERAS | B8: VIATICOS POLCA | C8: VIATICOS POLCA - AÑO 2026 - NUEVO CONVENIO | M8: =SUM(N8:Y8) -> 1.429377e+09 | N8: 115086719 | O8: 115086719 | P8: 115086719 | Q8: 115086719 | R8: 115086719 | S8: 115086719 | T8: 1.2314279e+08 | U8: 1.2314279e+08 | V8: 1.2314279e+08 | W8: 1.2314279e+08 | X8: 1.2314279e+08 | Y8: 1.2314279e+08
A9: POLICIA DE CARRETERAS | B9: MANTENIMIENTO EQUIPOS POLCA | C9: MANTENIMIENTO EQUIPOS POLCA AÑO 2026 - NUEVO CONVENIO | M9: =SUM(N9:Y9) -> 1.1807488e+09 | N9: 88491254 | O9: 1.4410319e+08 | P9: 74884833 | Q9: 60553175 | R9: 2.6469757e+08 | S9: 1.0312527e+08 | T9: 82837938 | U9: 57543095 | V9: 78261761 | W9: 81195372 | X9: 79919156 | Y9: 65136169
M10: =SUM(M8:M9) -> 2.6101258e+09
A12: OTRAS INVERSIONES - RESERVA - AFECTAN PRESUPUESTO 2025
A13: POLICIA DE CARRETERAS | B13: VIATICOS POLCA | C13: VIATICOS POLCA NO INVERTIDOS DIC-2022 A DIC-2025 (Reserva) | M13: =SUM(N13:Y13) -> 3271006358 | N13: 3271006358
M14: =SUM(M13:M13) -> 3271006358

Sheet Inversion Activos
B2: Variable
B3: IPC (dic/dic) | C3: 4,0%
B4: Salario mínimo | C4: 0.08
B5: TRM promedio (COP/USD) | C5: $4.250
A7: Capítulo | B7: ítem | C7: Insumo | D7: Descripción | E7: Unidad | F7: Cantidad 2026 | G7: Precio Base 2025 | H7: Precio Base 2026 | I7: Valor Total | J7: Supuestos | K7: Observaciones | L7: Soporte | M7: Total Presupuesto 2026 | N7: Enero | O7: febrero | P7: marzo | Q7: abril | R7: mayo | S7: junio | T7: julio | U7: agosto | V7: septiembre | W7: octubre | X7: noviembre | Y7: diciembre
A8: INVERSIÓN ACTIVOS | B8: CONVENIO POLCA | C8: EQUIPOS Y ELEMENTOS NUEVO CONVENIO 2026 | K8: indicar si existe algun valor por retoma y el año del equipo que se reemplaza | M8: 6.1832794e+09 | N8: 6.1832794e+09 | O8: 0 | P8: 0 | Q8: 0 | R8: 0 | S8: 0 | T8: 0 | U8: 0 | V8: 0 | W8: 0 | X8: 0 | Y8: 0
A9: INVERSIÓN ACTIVOS | B9: SISTEMAS ILUMINACIÓN | C9: CAMBIO LUMINARIAS TUNELES UF 2 (LAS JUNTAS Y EL INFIERNO) | K9: Indicar para que área será asignado, si el anterior se da de baja o se reasigna y el año del equipo | M9: =SUM(N9:Y9) -> 1300000000 | N9: 1300000000 | O9: 0 | P9: 0 | Q9: 0 | R9: 0 | S9: 0 | T9: 0 | U9: 0 | V9: 0 | W9: 0 | X9: 0 | Y9: 0
A10: INVERSIÓN ACTIVOS | B10: SISTEMAS DE ENERGÍA | C10: PROYECTOS DE EFICIENCIA ENERGETICA EDIFICACIONES (Optativo supeditado a conveniencia de amortización de inversión) | K10: Indicar para que área será asignado, si el anterior se da de baja o se reasigna y el año del equipo | M10: =SUM(N10:Y10) -> 1015000000 | N10: 1015000000 | O10: 0 | P10: 0 | Q10: 0 | R10: 0 | S10: 0 | T10: 0 | U10: 0 | V10: 0 | W10: 0 | X10: 0 | Y10: 0
M11: =SUM(M8:M10) -> 8.4982794e+09
A12: OTRAS INVERSIONES - RESERVA - AFECTAN PRESUPUESTO 2025
A13: INVERSIÓN ACTIVOS | B13: CONVENIO POLCA | C13: EQUIPOS Y ELEMENTOS - ACTA DE LIQUIDACIÓN CONVENIO 2016 A 2022 (Reserva) (Afecta Preupuesto 2025) | K13: indicar si existe algun valor por retoma y el año del equipo que se reemplaza | M13: 973966517 | N13: 973966517
A14: INVERSIÓN ACTIVOS | B14: CONVENIO POLCA | C14: ELEMENTOS POLCA NO INVERTIDOS DIC-2022 A DIC-2025 (Reserva) (Afecta Preupuesto 2025) | K14: indicar si existe algun valor por retoma y el año del equipo que se reemplaza | M14: 3.2250365e+09 | N14: 3.2250365e+09
K15: indicar si existe algun valor por retoma y el año del equipo que se reemplaza | M15: =SUM(M13:M14) -> 4.199003e+09

Sheet Gestión Ambiental
B2: Variable
B3: IPC (dic/dic) | C3: 4,0%
B4: Salario mínimo | C4: 0.08
B5: TRM promedio (COP/USD) | C5: $4.250
A7: Capítulo | B7: ítem | C7: Insumo | D7: Descripción | E7: Unidad | F7: Cantidad 2026 | G7: Precio Base 2025 | H7: Precio Base 2026 | I7: Valor Total | J7: Supuestos | K7: Observaciones | L7: Soporte | M7: Total Presupuesto 2026 | N7: Enero | O7: febrero | P7: marzo | Q7: abril | R7: mayo | S7: junio | T7: julio | U7: agosto | V7: septiembre | W7: octubre | X7: noviembre | Y7: diciembre
A8: GESTION AMBIENTAL

Sheet Gestión Social
B2: Variable
B3: IPC (dic/dic) | C3: 4,0%
B4: Salario mínimo | C4: 0.08
B5: TRM promedio (COP/USD) | C5: $4.250
A7: Capítulo | B7: ítem | C7: Insumo | D7: Descripción | E7: Unidad | F7: Cantidad 2026 | G7: Precio Base 2025 | H7: Precio Base 2026 | I7: Valor Total | J7: Supuestos | K7: Observaciones | L7: Soporte | M7: Total Presupuesto 2026 | N7: Enero | O7: febrero | P7: marzo | Q7: abril | R7: mayo | S7: junio | T7: julio | U7: agosto | V7: septiembre | W7: octubre | X7: noviembre | Y7: diciembre
A8: GESTION SOCIAL

Sheet Gestión Predial
B2: Variable
B3: IPC (dic/dic) | C3: 4,0%
B4: Salario mínimo | C4: 0.08
B5: TRM promedio (COP/USD) | C5: $4.250
A7: Capítulo | B7: ítem | C7: Insumo | D7: Descripción | E7: Unidad | F7: Cantidad 2026 | G7: Precio Base 2025 | H7: Precio Base 2026 | I7: Valor Total | J7: Supuestos | K7: Observaciones | L7: Soporte | M7: Total Presupuesto 2026 | N7: Enero | O7: febrero | P7: marzo | Q7: abril | R7: mayo | S7: junio | T7: julio | U7: agosto | V7: septiembre | W7: octubre | X7: noviembre | Y7: diciembre
A8: GESTION PREDIAL

Sheet Jurídica
B2: Variable
B3: IPC (dic/dic) | C3: 4,0%
B4: Salario mínimo | C4: 0.08
B5: TRM promedio (COP/USD) | C5: $4.250
A7: Capítulo | B7: ítem | C7: Insumo | D7: Descripción | E7: Unidad | F7: Cantidad 2026 | G7: Precio Base 2025 | H7: Precio Base 2026 | I7: Valor Total | J7: Supuestos | K7: Observaciones | L7: Soporte | M7: Total Presupuesto 2026 | N7: Enero | O7: febrero | P7: marzo | Q7: abril | R7: mayo | S7: junio | T7: julio | U7: agosto | V7: septiembre | W7: octubre | X7: noviembre | Y7: diciembre
A8: JURIDICA

Sheet SST
B2: Variable
B3: IPC (dic/dic) | C3: 4,0%
B4: Salario mínimo | C4: 0.08
B5: TRM promedio (COP/USD) | C5: $4.250
A7: Capítulo | B7: ítem | C7: Insumo | D7: Descripción | E7: Unidad | F7: Cantidad 2026 | G7: Precio Base 2025 | H7: Precio Base 2026 | I7: Valor Total | J7: Supuestos | K7: Observaciones | L7: Soporte | M7: Total Presupuesto 2026 | N7: Enero | O7: febrero | P7: marzo | Q7: abril | R7: mayo | S7: junio | T7: julio | U7: agosto | V7: septiembre | W7: octubre | X7: noviembre | Y7: diciembre
A8: =Capítulos!A4 -> SST | B8: DOTACION | C8: CAMISAS MUJER BLANCA TALLA XS | H8: =G8*(1+$C$3) -> 0 | I8: =+F8*H8 -> 0
A9: SST | B9: DOTACION | C9: CAMISAS MUJER BLANCA TALLA S | H9: =G9*(1+$C$3) -> 0 | I9: =+F9*H9 -> 0
A10: SST | B10: DOTACION | C10: CAMISAS HOMBRE BLANCAS TALLA L | H10: =G10*(1+$C$3) -> 0 | I10: =+F10*H10 -> 0
A11: SST | B11: DOTACION | C11: CAMISAS HOMBRE BLANCAS TALLA XL | H11: =G11*(1+$C$3) -> 0 | I11: =+F11*H11 -> 0
A12: SST | B12: DOTACION | C12: CAMISAS HOMBRE AZUL TALLA L 0 CONSERJE | H12: =G12*(1+$C$3) -> 0 | I12: =+F12*H12 -> 0
A13: SST | B13: DOTACION | C13: CAMISAS HOMBRE AZUL TALLA XL 0 CONSERJE | H13: =G13*(1+$C$3) -> 0 | I13: =+F13*H13 -> 0
A14: SST | B14: DOTACION | C14: PANTALÓN JEANS MUJER TALLA 10 | H14: =G14*(1+$C$3) -> 0 | I14: =+F14*H14 -> 0
A15: SST | B15: DOTACION | C15: PANTALÓN JEANS MUJER TALLA 12 | H15: =G15*(1+$C$3) -> 0 | I15: =+F15*H15 -> 0
A16: SST | B16: DOTACION | C16: PANTALÓN JEANS HOMBRE TALLA 40 | H16: =G16*(1+$C$3) -> 0 | I16: =+F16*H16 -> 0
A17: SST | B17: DOTACION | C17: PANTALÓN JEANS HOMBRE TALLA 42 | H17: =G17*(1+$C$3) -> 0 | I17: =+F17*H17 -> 0
A18: SST | B18: DOTACION | C18: CHAQUETA TALLA XL DAMA | H18: =G18*(1+$C$3) -> 0 | I18: =+F18*H18 -> 0
A19: SST | B19: DOTACION | C19: CHAQUETA TALLA XXL HOMBRE | H19: =G19*(1+$C$3) -> 0 | I19: =+F19*H19 -> 0
A20: SST | B20: DOTACION | C20: CONJUNTO ANTIFLUIDO TALLA S | H20: =G20*(1+$C$3) -> 0 | I20: =+F20*H20 -> 0
... A28: SST | B28: EPPS | C28: GASCOS | H28: =G28*(1+$C$3) -> 0 | I28: =+F28*H28 -> 0

Sheet Pólizas
B2: Variable
B3: IPC (dic/dic) | C3: 4,0%
B4: Salario mínimo | C4: 0.08
B5: TRM promedio (COP/USD) | C5: $4.250
A7: Capítulo | B7: ítem | C7: Insumo | D7: Descripción | E7: Unidad | F7: Cantidad 2026 | G7: Precio Base 2025 | H7: Precio Base 2026 | I7: Valor Total | J7: Supuestos | K7: Observaciones | L7: Soporte | M7: Total Presupuesto 2026 | N7: Enero | O7: febrero | P7: marzo | Q7: abril | R7: mayo | S7: junio | T7: julio | U7: agosto | V7: septiembre | W7: octubre | X7: noviembre | Y7: diciembre
A8: POLIZAS | B8: CUMPLIMIENTO
A9: POLIZAS | B9: SALARIOS Y PRESTACIONES SOCIALES
A10: POLIZAS | B10: ESTABILIDAD Y CALIDAD
A11: POLIZAS | B11: D&O
A12: POLIZAS | B12: AUTOS
A13: POLIZAS | B13: RC AMBIENTAL
A14: POLIZAS | B14: RESPONSABILIDAD CIVIL EXTRACONTRACTUAL
A15: POLIZAS | B15: OBRA CIVIL TERMINADA
A16: POLIZAS | B16: TODO RIESGO CONSTRUCCION

Sheet Administración
B2: Variable
B3: IPC (dic/dic) | C3: 4,0%
B4: Salario mínimo | C4: 0.08
B5: TRM promedio (COP/USD) | C5: $4.250
A7: Capítulo | B7: ítem | C7: Insumo | D7: Descripción | E7: Unidad | F7: Cantidad 2026 | G7: Precio Base 2025 | H7: Precio Base 2026 | I7: Valor Total | J7: Supuestos | K7: Observaciones | L7: Soporte | M7: Total Presupuesto 2026 | N7: Enero | O7: febrero | P7: marzo | Q7: abril | R7: mayo | S7: junio | T7: julio | U7: agosto | V7: septiembre | W7: octubre | X7: noviembre | Y7: diciembre
A8: =Capítulos!$A$2 -> ADMINISTRACION | B8: GASTOS GENERALES OFICINA BOGOTÁ | C8: ARRENDAMIENTO OFICINA | D8: Arrendamiento oficina Teleport 502 | E8: Mes | F8: 12 | G8: 11305000 | H8: =G8*(1+$C$3) -> 11757200 | I8: =+F8*H8 -> 141086400 | J8: Consumo estimado para el año 2026 | K8: precio según contrato | L8: Contrato de Arrendamiento suscrito en 2025 | M8: =SUM(N8:Y8) -> 141086400 | N8: =+I8/$F8 -> 11757200 | O8: =+$I$8/$F$8 -> 11757200 | P8: =+$I$8/$F$8 -> 11757200 | Q8: =+$I$8/$F$8 -> 11757200 | R8: =+$I$8/$F$8 -> 11757200 | S8: =+$I$8/$F$8 -> 11757200 | T8: =+$I$8/$F$8 -> 11757200 | U8: =+$I$8/$F$8 -> 11757200 | V8: =+$I$8/$F$8 -> 11757200 | ... Y8: =+$I$8/$F$8 -> 11757200
A9: =Capítulos!$A$2 -> ADMINISTRACION | B9: GASTOS GENERALES OFICINA BOGOTÁ | C9: ADMINISTRACIÓN OFICINA | D9: Administración oficina Teleport 502 | E9: Mes | F9: 12 | G9: 2258812 | H9: =G9*(1+$C$3) -> 2349164.5 | I9: =+F9*H9 -> 28189974 | J9: Consumo estimado para el año 2026 | K9: precio según contrato | L9: Contrato de Administración suscrito en 2025 | M9: =SUM(N9:Y9) -> 28189974 | N9: =+$I$9/$F$9 -> 2349164.5 | O9: =+$I$9/$F$9 -> 2349164.5 | P9: =+$I$9/$F$9 -> 2349164.5 | Q9: =+$I$9/$F$9 -> 2349164.5 | R9: =+$I$9/$F$9 -> 2349164.5 | S9: =+$I$9/$F$9 -> 2349164.5 | T9: =+$I$9/$F$9 -> 2349164.5 | U9: =+$I$9/$F$9 -> 2349164.5 | ... Y9: =+$I$9/$F$9 -> 2349164.5
A10: =Capítulos!$A$2 -> ADMINISTRACION | B10: GASTOS PAPELERIA OFICINA BOGOTÁ | C10: ALMOHADILLA DACTILAR | D10: Almohadilla X 4000 Huellas | E10: unidad | F10: 10 | G10: 5000 | H10: =G10*(1+$C$3) -> 5200 | I10: =+F10*H10 -> 52000 | J10: Consumo estimado para el año 2026 | K10: Precio promedio de mercado | L10: Cotización | M10: =SUM(N10:Y10) -> 52000 | O10: =+$I$10/3 -> 17333.333 | S10: =+$I$10/3 -> 17333.333 | W10: =+$I$10/3 -> 17333.333
A11: =Capítulos!$A$2 -> ADMINISTRACION | B11: GASTOS PAPELERIA OFICINA BOGOTÁ | C11: AZ CARTA AZUL PLASTIFICADO | D11: AZ para archivo | E11: unidad | F11: 500 | G11: 700 | H11: =G11*(1+$C$3) -> 728 | I11: =+F11*H11 -> 364000 | J11: Consumo estimado para el año 2026 | K11: Precio promedio de mercado | L11: Cotización | M11: =SUM(N11:Y11) -> 364000 | O11: =+$I$11/3 -> 121333.33 | S11: =+$I$11/3 -> 121333.33 | W11: =+$I$11/3 -> 121333.33
A12: =Capítulos!$A$2 -> ADMINISTRACION | B12: GASTOS PAPELERIA OFICINA BOGOTÁ | C12: AZ OFICIO AZUL PLASTIFICADO | D12: AZ para archivo | E12: unidad | F12: 1000 | G12: 800 | H12: =G12*(1+$C$3) -> 832 | I12: =+F12*H12 -> 832000 | J12: Consumo estimado para el año 2026 | K12: Precio promedio de mercado | L12: Cotización | M12: =SUM(N12:Y12) -> 832000 | O12: =+$I$12/3 -> 277333.33 | S12: =+$I$12/3 -> 277333.33 | W12: =+$I$12/3 -> 277333.33
A13: =Capítulos!$A$2 -> ADMINISTRACION | B13: GASTOS PAPELERIA OFICINA BOGOTÁ | C13: BANDERITAS COLORES | D13: Banderitas por 5 unidades paquete | E13: unidad | F13: 10 | G13: 4000 | H13: =G13*(1+$C$3) -> 4160 | I13: =+F13*H13 -> 41600 | J13: Consumo estimado para el año 2026 para las 5 sedes | K13: Precio promedio de mercado | L13: Cotización | M13: =SUM(N13:Y13) -> 41600 | O13: =+$I$13/3 -> 13866.667 | S13: =+$I$13/3 -> 13866.667 | W13: =+$I$13/3 -> 13866.667
A14: =Capítulos!$A$2 -> ADMINISTRACION | B14: GASTOS PAPELERIA OFICINA BOGOTÁ | C14: BISTURI GRANDE PLASTICO | H14: =G14*(1+$C$3) -> 0 | I14: =+F14*H14 -> 0 | M14: =SUM(N14:Y14) -> 0
A15: =Capítulos!$A$2 -> ADMINISTRACION | B15: GASTOS PAPELERIA OFICINA BOGOTÁ | C15: BLOCK AMARILLO MEDIA CARTA CUADRICULADO 50H | H15: =G15*(1+$C$3) -> 0 | I15: =+F15*H15 -> 0 | M15: =SUM(N15:Y15) -> 0
A16: =Capítulos!$A$2 -> ADMINISTRACION | B16: GASTOS PAPELERIA OFICINA BOGOTÁ | C16: BLOCK IRIS CARTA X 35 HOJAS | H16: =G16*(1+$C$3) -> 0 | I16: =+F16*H16 -> 0 | M16: =SUM(N16:Y16) -> 0
A17: =Capítulos!$A$2 -> ADMINISTRACION | B17: GASTOS PAPELERIA OFICINA BOGOTÁ | C17: BLOCK MILIMETRADO OFICIO 25H | H17: =G17*(1+$C$3) -> 0 | I17: =+F17*H17 -> 0 | M17: =SUM(N17:Y17) -> 0
A18: =Capítulos!$A$2 -> ADMINISTRACION | B18: GASTOS PAPELERIA OFICINA BOGOTÁ | C18: BOLSA DE VINILO CARTA DELGADA PAQUETE X 20 UND | H18: =G18*(1+$C$3) -> 0 | I18: =+F18*H18 -> 0 | M18: =SUM(N18:Y18) -> 0
A19: =Capítulos!$A$2 -> ADMINISTRACION | B19: GASTOS GENERALES OFICINA CCO | H19: =G19*(1+$C$3) -> 0 | I19: =+F19*H19 -> 0
A20: =Capítulos!$A$2 -> ADMINISTRACION | B20: GASTOS GENERALES AREA SERVICIOS SLG | H20: =G20*(1+$C$3) -> 0 | I20: =+F20*H20 -> 0
A21: =Capítulos!$A$2 -> ADMINISTRACION | B21: GASTOS GENERALES AREA SERVICIOS MACHETA | H21: =G21*(1+$C$3) -> 0 | I21: =+F21*H21 -> 0
A22: =Capítulos!$A$2 -> ADMINISTRACION | B22: GASTOS GENERALES PEAJE SLG | H22: =G22*(1+$C$3) -> 0 | I22: =+F22*H22 -> 0
A23: =Capítulos!$A$2 -> ADMINISTRACION | B23: GASTOS GENERALES PEAJE MACHETA | H23: =G23*(1+$C$3) -> 0 | I23: =+F23*H23 -> 0
A24: =Capítulos!$A$2 -> ADMINISTRACION | B24: BAÑOS MOVILES | H24: =G24*(1+$C$3) -> 0 | I24: =+F24*H24 -> 0
A25: =Capítulos!$A$2 -> ADMINISTRACION | B25: ASESORIAS Y AFILIACIONES | H25: =G25*(1+$C$3) -> 0 | I25: =+F25*H25 -> 0

Sheet Financiera
B2: Variable
B3: IPC (dic/dic) | C3: 4,0%
B4: Salario mínimo | C4: 0.08
B5: TRM promedio (COP/USD) | C5: $4.250
A7: Capítulo | B7: ítem | C7: Insumo | D7: Descripción | E7: Unidad | F7: Cantidad 2026 | G7: Precio Base 2025 | H7: Precio Base 2026 | I7: Valor Total | J7: Supuestos | K7: Observaciones | L7: Soporte | M7: Total Presupuesto 2026 | N7: Enero | O7: febrero | P7: marzo | Q7: abril | R7: mayo | S7: junio | T7: julio | U7: agosto | V7: septiembre | W7: octubre | X7: noviembre | Y7: diciembre
A8: FINANCIERA | B8: COSTOS FINANCIEROS
A9: FINANCIERA | B9: COMISION FIDUCIARIA
A10: FINANCIERA | B10: HONORARIOS AGENTE ADMINISTRATIVO
A11: FINANCIERA | B11: HONORARIOS AGENTE ADMINISTRATIVO LIQUIDEZ
A12: FINANCIERA | B12: HONORARIOS AGENTE GARANTÍAS
A13: FINANCIERA | B13: CUARTO DE DATOS
A14: FINANCIERA | B14: ASESOR LEGAL PRESTAMISTA
A15: FINANCIERA | B15: ASESOR LEGAL DEUDOR
A16: FINANCIERA | B16: INGENIERO INDEPENDIENTE | C16: ADICIONAL CERTIFICADO CAMBIO CLIMATICO
A17: FINANCIERA | B17: INGENIERO INDEPENDIENTE | C17: MEMO REVISION PRESUPUESTO
A18: FINANCIERA | B18: INGENIERO INDEPENDIENTE | C18: CERTIFICADO DISPENSA WAIVER
A19: FINANCIERA | B19: INGENIERO INDEPENDIENTE | C19: REVISION PLAN DE OBRA HITOS
A20: FINANCIERA | B20: INGENIERO INDEPENDIENTE | C20: INFORME SEMESTRAL TECNICO OPERACION
A21: FINANCIERA | B21: INGENIERO INDEPENDIENTE | C21: INFORME SEMESTRAL SOCIO AMBIENTAL OPERACION
A22: FINANCIERA | B22: PAGO CAPITAL DEUDA
A23: FINANCIERA | B23: PAGO INTERESES DEUDA
A24: FINANCIERA | B24: HONORARIOS REVISOR FISCAL
A25: FINANCIERA | B25: HONORARIOS AUDITOR EXTERNO
A26: FINANCIERA | B26: HONORARIOS CONSULTAS TRIBUTARIAS
A27: FINANCIERA | B27: HONORARIOS CONSULTAS niif
A28: FINANCIERA | B28: AGENTE DE CALCULO TERMINACION
A29: FINANCIERA | B29: ACTUALIZACIÓN MODELO FINANCIERO
A30: FINANCIERA | B30: AUDITORIA MDELO FINANCIERO
A31: FINANCIERA | B31: CAMARA DE COMERCIO

Sheet Fondeos
B2: Variable
B3: IPC (dic/dic) | C3: 4,0%
B4: Salario mínimo | C4: 0.08
B5: TRM promedio (COP/USD) | C5: $4.250
A7: Capítulo | B7: ítem | C7: Insumo | D7: Descripción | E7: Unidad | F7: Cantidad 2026 | G7: Precio Base 2025 | H7: Precio Base 2026 | I7: Valor Total | J7: Supuestos | K7: Observaciones | L7: Soporte | M7: Total Presupuesto 2026 | N7: Enero | O7: febrero | P7: marzo | Q7: abril | R7: mayo | S7: junio | T7: julio | U7: agosto | V7: septiembre | W7: octubre | X7: noviembre | Y7: diciembre
A8: FONDEOS | B8: INTERVENTORIA Y SUPERVISION
A9: FONDEOS | B9: SOPORTE CONSTRACTUAL
A10: FONDEOS | B10: APORTE ANUAL -MASC
A11: FONDEOS | B11: PRIMER APORTE SEMESTRAL -MASC

Sheet Impuestos 
B2: Variable
B3: IPC (dic/dic) | C3: 4,0%
B4: Salario mínimo | C4: 0.08
B5: TRM promedio (COP/USD) | C5: $4.250
A7: Capítulo | B7: ítem | C7: Insumo | D7: Descripción | E7: Unidad | F7: Cantidad 2026 | G7: Precio Base 2025 | H7: Precio Base 2026 | I7: Valor Total | J7: Supuestos | K7: Observaciones | L7: Soporte | M7: Total Presupuesto 2026 | N7: Enero | O7: febrero | P7: marzo | Q7: abril | R7: mayo | S7: junio | T7: julio | U7: agosto | V7: septiembre | W7: octubre | X7: noviembre | Y7: diciembre
A8: IMPUESTOS | B8: APORTE SUPER TRANSPORTE
A9: IMPUESTOS | B9: APORTE FONTUR
A10: IMPUESTOS | B10: APORTE FONSECON
A11: IMPUESTOS | B11: ICA
A12: IMPUESTOS | B12: ICA MUNICIPIOS
A13: IMPUESTOS | B13: AUTORETENCION
